{
"meta":{"test_sets":[],"test_metrics":[],"learn_metrics":[{"best_value":"Min","name":"Logloss"}],"launch_mode":"Train","parameters":"","iteration_count":1000,"learn_sets":["learn"],"name":"experiment"},
"iterations":[
{"learn":[0.6128554799],"iteration":0,"passed_time":0.07779831567,"remaining_time":77.72051736},
{"learn":[0.5505717046],"iteration":1,"passed_time":0.09393749995,"remaining_time":46.87481248},
{"learn":[0.5064195973],"iteration":2,"passed_time":0.1086492771,"remaining_time":36.10777641},
{"learn":[0.4731347061],"iteration":3,"passed_time":0.1229576402,"remaining_time":30.61645241},
{"learn":[0.4459045608],"iteration":4,"passed_time":0.1382699966,"remaining_time":27.51572933},
{"learn":[0.4260985597],"iteration":5,"passed_time":0.1538146015,"remaining_time":25.48195232},
{"learn":[0.4106076899],"iteration":6,"passed_time":0.1672909702,"remaining_time":23.73141906},
{"learn":[0.3969883439],"iteration":7,"passed_time":0.1849083946,"remaining_time":22.92864094},
{"learn":[0.3830210015],"iteration":8,"passed_time":0.1986281367,"remaining_time":21.87116483},
{"learn":[0.3708963943],"iteration":9,"passed_time":0.2138248272,"remaining_time":21.1686579},
{"learn":[0.3601239441],"iteration":10,"passed_time":0.2304168002,"remaining_time":20.71656503},
{"learn":[0.3524731463],"iteration":11,"passed_time":0.2466070674,"remaining_time":20.30398189},
{"learn":[0.3416593593],"iteration":12,"passed_time":0.2629734585,"remaining_time":19.96575412},
{"learn":[0.3346056971],"iteration":13,"passed_time":0.2756877073,"remaining_time":19.41629138},
{"learn":[0.3289640662],"iteration":14,"passed_time":0.2874252542,"remaining_time":18.87425836},
{"learn":[0.3185105509],"iteration":15,"passed_time":0.3019656158,"remaining_time":18.57088537},
{"learn":[0.3125702847],"iteration":16,"passed_time":0.3145181989,"remaining_time":18.18655232},
{"learn":[0.3085995335],"iteration":17,"passed_time":0.327923318,"remaining_time":17.89003879},
{"learn":[0.3037890904],"iteration":18,"passed_time":0.343250716,"remaining_time":17.72257644},
{"learn":[0.2960310227],"iteration":19,"passed_time":0.3559912146,"remaining_time":17.44356952},
{"learn":[0.2903429274],"iteration":20,"passed_time":0.3721904402,"remaining_time":17.35116385},
{"learn":[0.2862622922],"iteration":21,"passed_time":0.3864794284,"remaining_time":17.18076732},
{"learn":[0.2806849587],"iteration":22,"passed_time":0.404431309,"remaining_time":17.17953865},
{"learn":[0.276894813],"iteration":23,"passed_time":0.4180727182,"remaining_time":17.00162387},
{"learn":[0.2688055929],"iteration":24,"passed_time":0.4354863523,"remaining_time":16.98396774},
{"learn":[0.2628612649],"iteration":25,"passed_time":0.4479641443,"remaining_time":16.78142602},
{"learn":[0.2601627812],"iteration":26,"passed_time":0.4614028049,"remaining_time":16.62758997},
{"learn":[0.2574708263],"iteration":27,"passed_time":0.4756492517,"remaining_time":16.51182402},
{"learn":[0.2499552832],"iteration":28,"passed_time":0.4928753455,"remaining_time":16.50282622},
{"learn":[0.2466331921],"iteration":29,"passed_time":0.5097288167,"remaining_time":16.48123174},
{"learn":[0.2434030836],"iteration":30,"passed_time":0.5244266772,"remaining_time":16.39256291},
{"learn":[0.240254904],"iteration":31,"passed_time":0.5384697921,"remaining_time":16.28871121},
{"learn":[0.2377431424],"iteration":32,"passed_time":0.554362603,"remaining_time":16.24450415},
{"learn":[0.2348196029],"iteration":33,"passed_time":0.5677866803,"remaining_time":16.13182157},
{"learn":[0.2322205843],"iteration":34,"passed_time":0.5846081517,"remaining_time":16.1184819},
{"learn":[0.2289202354],"iteration":35,"passed_time":0.5972586926,"remaining_time":15.99326055},
{"learn":[0.2260792397],"iteration":36,"passed_time":0.6101105654,"remaining_time":15.87936417},
{"learn":[0.2228290076],"iteration":37,"passed_time":0.6251296738,"remaining_time":15.82565122},
{"learn":[0.220214411],"iteration":38,"passed_time":0.6410627344,"remaining_time":15.79644328},
{"learn":[0.2159909089],"iteration":39,"passed_time":0.6571642523,"remaining_time":15.77194206},
{"learn":[0.2136529233],"iteration":40,"passed_time":0.6716052812,"remaining_time":15.70901133},
{"learn":[0.21167576],"iteration":41,"passed_time":0.6859730189,"remaining_time":15.64671791},
{"learn":[0.207563529],"iteration":42,"passed_time":0.7011213765,"remaining_time":15.60402691},
{"learn":[0.2059948549],"iteration":43,"passed_time":0.7145028708,"remaining_time":15.52419874},
{"learn":[0.2044739397],"iteration":44,"passed_time":0.7299574763,"remaining_time":15.49131977},
{"learn":[0.1982472626],"iteration":45,"passed_time":0.7411376102,"remaining_time":15.37054957},
{"learn":[0.1959049533],"iteration":46,"passed_time":0.7535006113,"remaining_time":15.27842729},
{"learn":[0.1948188553],"iteration":47,"passed_time":0.7671115207,"remaining_time":15.21437849},
{"learn":[0.1922150573],"iteration":48,"passed_time":0.7788746091,"remaining_time":15.11652558},
{"learn":[0.1907566729],"iteration":49,"passed_time":0.7925176433,"remaining_time":15.05783522},
{"learn":[0.1890873077],"iteration":50,"passed_time":0.8087729102,"remaining_time":15.04951945},
{"learn":[0.1879711189],"iteration":51,"passed_time":0.8214200344,"remaining_time":14.97511909},
{"learn":[0.1861382619],"iteration":52,"passed_time":0.8339709925,"remaining_time":14.90133075},
{"learn":[0.1849673453],"iteration":53,"passed_time":0.8464972842,"remaining_time":14.82937835},
{"learn":[0.1838716289],"iteration":54,"passed_time":0.8647672043,"remaining_time":14.85827287},
{"learn":[0.1823869796],"iteration":55,"passed_time":0.8774957029,"remaining_time":14.79207042},
{"learn":[0.1811231635],"iteration":56,"passed_time":0.8891791252,"remaining_time":14.71045465},
{"learn":[0.1774582612],"iteration":57,"passed_time":0.9025668278,"remaining_time":14.6589302},
{"learn":[0.1753573997],"iteration":58,"passed_time":0.9183012647,"remaining_time":14.64612695},
{"learn":[0.1741845612],"iteration":59,"passed_time":0.9306992239,"remaining_time":14.58095451},
{"learn":[0.1709795145],"iteration":60,"passed_time":0.9470309486,"remaining_time":14.57806657},
{"learn":[0.1689934614],"iteration":61,"passed_time":0.9626393864,"remaining_time":14.56380233},
{"learn":[0.167021247],"iteration":62,"passed_time":0.978481031,"remaining_time":14.5529639},
{"learn":[0.1654825081],"iteration":63,"passed_time":0.9932163496,"remaining_time":14.52578911},
{"learn":[0.164364565],"iteration":64,"passed_time":1.007344339,"remaining_time":14.49026088},
{"learn":[0.1631699889],"iteration":65,"passed_time":1.021570078,"remaining_time":14.45676443},
{"learn":[0.1628062775],"iteration":66,"passed_time":1.027975993,"remaining_time":14.31494928},
{"learn":[0.1609523016],"iteration":67,"passed_time":1.041039573,"remaining_time":14.26836591},
{"learn":[0.1596712921],"iteration":68,"passed_time":1.055844516,"remaining_time":14.24624992},
{"learn":[0.157824828],"iteration":69,"passed_time":1.069391884,"remaining_time":14.20763504},
{"learn":[0.1566238502],"iteration":70,"passed_time":1.083413208,"remaining_time":14.17592775},
{"learn":[0.1551894517],"iteration":71,"passed_time":1.098433483,"remaining_time":14.15758711},
{"learn":[0.1540277945],"iteration":72,"passed_time":1.111551937,"remaining_time":14.11518693},
{"learn":[0.1528703407],"iteration":73,"passed_time":1.124805641,"remaining_time":14.07527058},
{"learn":[0.1518338953],"iteration":74,"passed_time":1.137487181,"remaining_time":14.02900857},
{"learn":[0.1494305914],"iteration":75,"passed_time":1.151019008,"remaining_time":13.99396794},
{"learn":[0.1469540512],"iteration":76,"passed_time":1.168390684,"remaining_time":14.0055143},
{"learn":[0.1447817595],"iteration":77,"passed_time":1.180470937,"remaining_time":13.95377184},
{"learn":[0.1437431817],"iteration":78,"passed_time":1.193305935,"remaining_time":13.91183248},
{"learn":[0.1424824052],"iteration":79,"passed_time":1.206580722,"remaining_time":13.8756783},
{"learn":[0.1412751018],"iteration":80,"passed_time":1.219592427,"remaining_time":13.8371042},
{"learn":[0.1399785358],"iteration":81,"passed_time":1.232807714,"remaining_time":13.8014327},
{"learn":[0.1396095248],"iteration":82,"passed_time":1.246152667,"remaining_time":13.76773488},
{"learn":[0.1378070081],"iteration":83,"passed_time":1.260026533,"remaining_time":13.74028933},
{"learn":[0.1370461702],"iteration":84,"passed_time":1.272722573,"remaining_time":13.70048417},
{"learn":[0.1360755562],"iteration":85,"passed_time":1.285484988,"remaining_time":13.66201487},
{"learn":[0.1350397471],"iteration":86,"passed_time":1.299145022,"remaining_time":13.63355638},
{"learn":[0.1335929514],"iteration":87,"passed_time":1.311556981,"remaining_time":13.59249963},
{"learn":[0.1326110534],"iteration":88,"passed_time":1.324108815,"remaining_time":13.55351831},
{"learn":[0.1314969762],"iteration":89,"passed_time":1.336752147,"remaining_time":13.51604949},
{"learn":[0.1304685229],"iteration":90,"passed_time":1.35084972,"remaining_time":13.4936527},
{"learn":[0.1294499214],"iteration":91,"passed_time":1.362884807,"remaining_time":13.45108048},
{"learn":[0.1284839467],"iteration":92,"passed_time":1.374980309,"remaining_time":13.4097542},
{"learn":[0.1269018971],"iteration":93,"passed_time":1.39145695,"remaining_time":13.41127656},
{"learn":[0.1262941042],"iteration":94,"passed_time":1.405333774,"remaining_time":13.38765332},
{"learn":[0.1252126335],"iteration":95,"passed_time":1.41816248,"remaining_time":13.35436336},
{"learn":[0.1237286756],"iteration":96,"passed_time":1.431771681,"remaining_time":13.32876112},
{"learn":[0.1225549774],"iteration":97,"passed_time":1.45125751,"remaining_time":13.35749259},
{"learn":[0.1206708849],"iteration":98,"passed_time":1.465000169,"remaining_time":13.33298133},
{"learn":[0.1197020177],"iteration":99,"passed_time":1.476671466,"remaining_time":13.29004319},
{"learn":[0.1191002],"iteration":100,"passed_time":1.492316904,"remaining_time":13.28309798},
{"learn":[0.1179555637],"iteration":101,"passed_time":1.50517136,"remaining_time":13.2514106},
{"learn":[0.116811367],"iteration":102,"passed_time":1.520185385,"remaining_time":13.23889602},
{"learn":[0.1157190846],"iteration":103,"passed_time":1.537036148,"remaining_time":13.24215758},
{"learn":[0.1148510742],"iteration":104,"passed_time":1.550638891,"remaining_time":13.21735054},
{"learn":[0.1139298067],"iteration":105,"passed_time":1.570770465,"remaining_time":13.24781883},
{"learn":[0.1131438957],"iteration":106,"passed_time":1.583154424,"remaining_time":13.21268132},
{"learn":[0.1125954563],"iteration":107,"passed_time":1.597505287,"remaining_time":13.19421033},
{"learn":[0.1119378651],"iteration":108,"passed_time":1.610479951,"remaining_time":13.16456547},
{"learn":[0.1112516157],"iteration":109,"passed_time":1.624180776,"remaining_time":13.14109901},
{"learn":[0.1090981011],"iteration":110,"passed_time":1.640465001,"remaining_time":13.13849897},
{"learn":[0.1076442045],"iteration":111,"passed_time":1.653927078,"remaining_time":13.11327898},
{"learn":[0.1063102519],"iteration":112,"passed_time":1.667930485,"remaining_time":13.09251629},
{"learn":[0.1052336036],"iteration":113,"passed_time":1.68491708,"remaining_time":13.09505731},
{"learn":[0.1047198414],"iteration":114,"passed_time":1.698480698,"remaining_time":13.07091668},
{"learn":[0.1039242577],"iteration":115,"passed_time":1.711669277,"remaining_time":13.04410036},
{"learn":[0.102449707],"iteration":116,"passed_time":1.725942599,"remaining_time":13.02570355},
{"learn":[0.101796244],"iteration":117,"passed_time":1.73786202,"remaining_time":12.98978222},
{"learn":[0.1010156142],"iteration":118,"passed_time":1.752033092,"remaining_time":12.97093407},
{"learn":[0.09998725457],"iteration":119,"passed_time":1.769145062,"remaining_time":12.97373045},
{"learn":[0.09931966775],"iteration":120,"passed_time":1.784095879,"remaining_time":12.96049816},
{"learn":[0.09818066579],"iteration":121,"passed_time":1.797070417,"remaining_time":12.93301497},
{"learn":[0.09745371464],"iteration":122,"passed_time":1.809730167,"remaining_time":12.90352322},
{"learn":[0.09709450014],"iteration":123,"passed_time":1.822904162,"remaining_time":12.87793586},
{"learn":[0.09526107049],"iteration":124,"passed_time":1.838429684,"remaining_time":12.86900779},
{"learn":[0.09508061396],"iteration":125,"passed_time":1.853915373,"remaining_time":12.8596987},
{"learn":[0.09424381049],"iteration":126,"passed_time":1.867980696,"remaining_time":12.84052872},
{"learn":[0.09355892063],"iteration":127,"passed_time":1.882624182,"remaining_time":12.82537724},
{"learn":[0.09241570467],"iteration":128,"passed_time":1.899471278,"remaining_time":12.82511227},
{"learn":[0.09035629484],"iteration":129,"passed_time":1.917441658,"remaining_time":12.83210956},
{"learn":[0.08936797247],"iteration":130,"passed_time":1.932960097,"remaining_time":12.82246049},
{"learn":[0.08895283298],"iteration":131,"passed_time":1.945832094,"remaining_time":12.79532014},
{"learn":[0.08773113257],"iteration":132,"passed_time":1.962932564,"remaining_time":12.79595889},
{"learn":[0.08686457104],"iteration":133,"passed_time":1.976267475,"remaining_time":12.77199726},
{"learn":[0.08653813875],"iteration":134,"passed_time":1.98957022,"remaining_time":12.74798696},
{"learn":[0.08569164174],"iteration":135,"passed_time":2.006416358,"remaining_time":12.7466451},
{"learn":[0.08446658959],"iteration":136,"passed_time":2.02314908,"remaining_time":12.74436245},
{"learn":[0.08362564009],"iteration":137,"passed_time":2.036712573,"remaining_time":12.72207419},
{"learn":[0.08256899768],"iteration":138,"passed_time":2.058374054,"remaining_time":12.75007238},
{"learn":[0.08197796894],"iteration":139,"passed_time":2.071934214,"remaining_time":12.72759588},
{"learn":[0.08111360555],"iteration":140,"passed_time":2.086031161,"remaining_time":12.70851608},
{"learn":[0.08081543391],"iteration":141,"passed_time":2.099555905,"remaining_time":12.68604906},
{"learn":[0.08030515154],"iteration":142,"passed_time":2.114970719,"remaining_time":12.67503431},
{"learn":[0.07984817253],"iteration":143,"passed_time":2.128179631,"remaining_time":12.65084558},
{"learn":[0.07944250708],"iteration":144,"passed_time":2.142039455,"remaining_time":12.63064644},
{"learn":[0.07899968993],"iteration":145,"passed_time":2.157032564,"remaining_time":12.61716308},
{"learn":[0.0783006498],"iteration":146,"passed_time":2.173535204,"remaining_time":12.61241857},
{"learn":[0.07801092108],"iteration":147,"passed_time":2.186895074,"remaining_time":12.58942299},
{"learn":[0.07759915004],"iteration":148,"passed_time":2.202854134,"remaining_time":12.5814018},
{"learn":[0.07689612693],"iteration":149,"passed_time":2.217942784,"remaining_time":12.56834244},
{"learn":[0.07599874501],"iteration":150,"passed_time":2.236395369,"remaining_time":12.57416999},
{"learn":[0.07543742193],"iteration":151,"passed_time":2.254620206,"remaining_time":12.57840747},
{"learn":[0.07501482858],"iteration":152,"passed_time":2.267219164,"remaining_time":12.55120675},
{"learn":[0.0746964167],"iteration":153,"passed_time":2.280389743,"remaining_time":12.52733586},
{"learn":[0.07422130678],"iteration":154,"passed_time":2.294793481,"remaining_time":12.51032575},
{"learn":[0.07392353365],"iteration":155,"passed_time":2.310507751,"remaining_time":12.50043937},
{"learn":[0.07341020633],"iteration":156,"passed_time":2.325674317,"remaining_time":12.48753789},
{"learn":[0.07306294537],"iteration":157,"passed_time":2.339316601,"remaining_time":12.46648467},
{"learn":[0.07260465567],"iteration":158,"passed_time":2.356900817,"remaining_time":12.46637476},
{"learn":[0.0722541685],"iteration":159,"passed_time":2.369609608,"remaining_time":12.44045044},
{"learn":[0.07165297296],"iteration":160,"passed_time":2.383295767,"remaining_time":12.41978353},
{"learn":[0.07106054144],"iteration":161,"passed_time":2.396173681,"remaining_time":12.39502188},
{"learn":[0.07072953495],"iteration":162,"passed_time":2.411485579,"remaining_time":12.38290448},
{"learn":[0.0703113261],"iteration":163,"passed_time":2.425304404,"remaining_time":12.36313708},
{"learn":[0.069907389],"iteration":164,"passed_time":2.445651935,"remaining_time":12.37648101},
{"learn":[0.06952536661],"iteration":165,"passed_time":2.458160102,"remaining_time":12.35003328},
{"learn":[0.06905044601],"iteration":166,"passed_time":2.474784075,"remaining_time":12.34428224},
{"learn":[0.0686948754],"iteration":167,"passed_time":2.488525817,"remaining_time":12.32412785},
{"learn":[0.06845715614],"iteration":168,"passed_time":2.502384308,"remaining_time":12.30462343},
{"learn":[0.06813418203],"iteration":169,"passed_time":2.51650063,"remaining_time":12.28644425},
{"learn":[0.06750003477],"iteration":170,"passed_time":2.529938333,"remaining_time":12.26502268},
{"learn":[0.06720339954],"iteration":171,"passed_time":2.547203426,"remaining_time":12.26211882},
{"learn":[0.06692666934],"iteration":172,"passed_time":2.563759608,"remaining_time":12.25566009},
{"learn":[0.06667471389],"iteration":173,"passed_time":2.577850806,"remaining_time":12.23738371},
{"learn":[0.06635787824],"iteration":174,"passed_time":2.592770623,"remaining_time":12.22306151},
{"learn":[0.06610989744],"iteration":175,"passed_time":2.606351783,"remaining_time":12.20246516},
{"learn":[0.06564459956],"iteration":176,"passed_time":2.620306315,"remaining_time":12.18368416},
{"learn":[0.06525281233],"iteration":177,"passed_time":2.632787107,"remaining_time":12.1581517},
{"learn":[0.06492856468],"iteration":178,"passed_time":2.647694299,"remaining_time":12.14389396},
{"learn":[0.06472772568],"iteration":179,"passed_time":2.663314529,"remaining_time":12.1328773},
{"learn":[0.06442897952],"iteration":180,"passed_time":2.678022722,"remaining_time":12.11768293},
{"learn":[0.06415895972],"iteration":181,"passed_time":2.691140968,"remaining_time":12.09534787},
{"learn":[0.06378090468],"iteration":182,"passed_time":2.704497171,"remaining_time":12.0741759},
{"learn":[0.06355694151],"iteration":183,"passed_time":2.717791999,"remaining_time":12.05281669},
{"learn":[0.06304273914],"iteration":184,"passed_time":2.7314957,"remaining_time":12.03334592},
{"learn":[0.0627332555],"iteration":185,"passed_time":2.74557319,"remaining_time":12.01557299},
{"learn":[0.06263953049],"iteration":186,"passed_time":2.761254335,"remaining_time":12.00481163},
{"learn":[0.06241491791],"iteration":187,"passed_time":2.775956279,"remaining_time":11.98976861},
{"learn":[0.06206735955],"iteration":188,"passed_time":2.791491926,"remaining_time":11.97830662},
{"learn":[0.06160531802],"iteration":189,"passed_time":2.806179953,"remaining_time":11.96318822},
{"learn":[0.06132495451],"iteration":190,"passed_time":2.8216386,"remaining_time":11.95133836},
{"learn":[0.06096838095],"iteration":191,"passed_time":2.835593466,"remaining_time":11.9331225},
{"learn":[0.06066520558],"iteration":192,"passed_time":2.849245291,"remaining_time":11.91368368},
{"learn":[0.06037124536],"iteration":193,"passed_time":2.865842264,"remaining_time":11.90654054},
{"learn":[0.05989318394],"iteration":194,"passed_time":2.878223849,"remaining_time":11.88189845},
{"learn":[0.0598615781],"iteration":195,"passed_time":2.897651636,"remaining_time":11.88628528},
{"learn":[0.0596422211],"iteration":196,"passed_time":2.913291907,"remaining_time":11.87499188},
{"learn":[0.05935960732],"iteration":197,"passed_time":2.926767484,"remaining_time":11.85488648},
{"learn":[0.05910362735],"iteration":198,"passed_time":2.940753141,"remaining_time":11.83690083},
{"learn":[0.05880265393],"iteration":199,"passed_time":2.954876214,"remaining_time":11.81950485},
{"learn":[0.05854434451],"iteration":200,"passed_time":2.970542984,"remaining_time":11.80827783},
{"learn":[0.05830836385],"iteration":201,"passed_time":2.983322066,"remaining_time":11.78559905},
{"learn":[0.05792783569],"iteration":202,"passed_time":2.998028468,"remaining_time":11.77058468},
{"learn":[0.05767395216],"iteration":203,"passed_time":3.015260812,"remaining_time":11.76542944},
{"learn":[0.05747279448],"iteration":204,"passed_time":3.030217712,"remaining_time":11.7513321},
{"learn":[0.05713511138],"iteration":205,"passed_time":3.044350993,"remaining_time":11.73405189},
{"learn":[0.05683831472],"iteration":206,"passed_time":3.057237032,"remaining_time":11.71202399},
{"learn":[0.05666251665],"iteration":207,"passed_time":3.072384682,"remaining_time":11.69869552},
{"learn":[0.05645120509],"iteration":208,"passed_time":3.08687621,"remaining_time":11.68286642},
{"learn":[0.0562280726],"iteration":209,"passed_time":3.099601959,"remaining_time":11.66040737},
{"learn":[0.05601677213],"iteration":210,"passed_time":3.114688234,"remaining_time":11.64686738},
{"learn":[0.0556844651],"iteration":211,"passed_time":3.128141352,"remaining_time":11.62724239},
{"learn":[0.05521474399],"iteration":212,"passed_time":3.142182259,"remaining_time":11.60984713},
{"learn":[0.05507767419],"iteration":213,"passed_time":3.157318242,"remaining_time":11.59650532},
{"learn":[0.0548309034],"iteration":214,"passed_time":3.170358196,"remaining_time":11.57549388},
{"learn":[0.05447642803],"iteration":215,"passed_time":3.187741664,"remaining_time":11.5703216},
{"learn":[0.05410385394],"iteration":216,"passed_time":3.201659322,"remaining_time":11.5525311},
{"learn":[0.05392817862],"iteration":217,"passed_time":3.215137148,"remaining_time":11.5331984},
{"learn":[0.05388441544],"iteration":218,"passed_time":3.234479186,"remaining_time":11.53483217},
{"learn":[0.05371556073],"iteration":219,"passed_time":3.250123082,"remaining_time":11.52316366},
{"learn":[0.05345543665],"iteration":220,"passed_time":3.264788235,"remaining_time":11.50800921},
{"learn":[0.0532164996],"iteration":221,"passed_time":3.281688497,"remaining_time":11.50069212},
{"learn":[0.05300655998],"iteration":222,"passed_time":3.294903618,"remaining_time":11.48044893},
{"learn":[0.05287245795],"iteration":223,"passed_time":3.310149475,"remaining_time":11.46730354},
{"learn":[0.05269016358],"iteration":224,"passed_time":3.325975119,"remaining_time":11.45613652},
{"learn":[0.05247807921],"iteration":225,"passed_time":3.340805729,"remaining_time":11.44152051},
{"learn":[0.05224762113],"iteration":226,"passed_time":3.352594234,"remaining_time":11.41654336},
{"learn":[0.05197196378],"iteration":227,"passed_time":3.366136519,"remaining_time":11.39762014},
{"learn":[0.05157797315],"iteration":228,"passed_time":3.380794046,"remaining_time":11.38249873},
{"learn":[0.05128922062],"iteration":229,"passed_time":3.395722905,"remaining_time":11.36828973},
{"learn":[0.05108004513],"iteration":230,"passed_time":3.412054047,"remaining_time":11.35874269},
{"learn":[0.05077103078],"iteration":231,"passed_time":3.428478021,"remaining_time":11.34944448},
{"learn":[0.0505529116],"iteration":232,"passed_time":3.442133513,"remaining_time":11.33097169},
{"learn":[0.05039292656],"iteration":233,"passed_time":3.4553833,"remaining_time":11.311212},
{"learn":[0.05021498761],"iteration":234,"passed_time":3.469953203,"remaining_time":11.29580511},
{"learn":[0.04999137195],"iteration":235,"passed_time":3.484544814,"remaining_time":11.28047559},
{"learn":[0.04970058614],"iteration":236,"passed_time":3.499911212,"remaining_time":11.26764664},
{"learn":[0.04947995457],"iteration":237,"passed_time":3.518220298,"remaining_time":11.26421793},
{"learn":[0.0492815664],"iteration":238,"passed_time":3.531175796,"remaining_time":11.24361833},
{"learn":[0.04906226754],"iteration":239,"passed_time":3.544762164,"remaining_time":11.22508018},
{"learn":[0.04886517357],"iteration":240,"passed_time":3.558832278,"remaining_time":11.20810664},
{"learn":[0.04877333762],"iteration":241,"passed_time":3.574105927,"remaining_time":11.19492683},
{"learn":[0.04861801922],"iteration":242,"passed_time":3.587213339,"remaining_time":11.17498147},
{"learn":[0.04836948729],"iteration":243,"passed_time":3.599349675,"remaining_time":11.15208342},
{"learn":[0.04815849079],"iteration":244,"passed_time":3.613884995,"remaining_time":11.13666601},
{"learn":[0.04789208726],"iteration":245,"passed_time":3.628068318,"remaining_time":11.12017688},
{"learn":[0.04780398319],"iteration":246,"passed_time":3.643915754,"remaining_time":11.10877961},
{"learn":[0.04762622261],"iteration":247,"passed_time":3.659761065,"remaining_time":11.09734},
{"learn":[0.04737303099],"iteration":248,"passed_time":3.672532938,"remaining_time":11.07659533},
{"learn":[0.04721779493],"iteration":249,"passed_time":3.687318632,"remaining_time":11.06195589},
{"learn":[0.04689657373],"iteration":250,"passed_time":3.703546232,"remaining_time":11.05161804},
{"learn":[0.04673360948],"iteration":251,"passed_time":3.718880672,"remaining_time":11.03858231},
{"learn":[0.04648773323],"iteration":252,"passed_time":3.733929447,"remaining_time":11.02468497},
{"learn":[0.04628848722],"iteration":253,"passed_time":3.749384344,"remaining_time":11.01197134},
{"learn":[0.04606836843],"iteration":254,"passed_time":3.76693756,"remaining_time":11.0053666},
{"learn":[0.04597468515],"iteration":255,"passed_time":3.780505345,"remaining_time":10.98709366},
{"learn":[0.0457967779],"iteration":256,"passed_time":3.793375384,"remaining_time":10.96684012},
{"learn":[0.04564702111],"iteration":257,"passed_time":3.808140244,"remaining_time":10.95209326},
{"learn":[0.04550407235],"iteration":258,"passed_time":3.824500219,"remaining_time":10.94190989},
{"learn":[0.04539088666],"iteration":259,"passed_time":3.83763384,"remaining_time":10.92249631},
{"learn":[0.0451949641],"iteration":260,"passed_time":3.850594212,"remaining_time":10.90264032},
{"learn":[0.04503274624],"iteration":261,"passed_time":3.865172823,"remaining_time":10.8873952},
{"learn":[0.04470865748],"iteration":262,"passed_time":3.879406895,"remaining_time":10.87118966},
{"learn":[0.04454411579],"iteration":263,"passed_time":3.89218856,"remaining_time":10.85094993},
{"learn":[0.04447558856],"iteration":264,"passed_time":3.909371779,"remaining_time":10.84297456},
{"learn":[0.04425020751],"iteration":265,"passed_time":3.926473957,"remaining_time":10.83470633},
{"learn":[0.04405474516],"iteration":266,"passed_time":3.943018347,"remaining_time":10.82484063},
{"learn":[0.04381060239],"iteration":267,"passed_time":3.95583322,"remaining_time":10.8047385},
{"learn":[0.04358386074],"iteration":268,"passed_time":3.967838557,"remaining_time":10.78249065},
{"learn":[0.04338682651],"iteration":269,"passed_time":3.98119501,"remaining_time":10.76397169},
{"learn":[0.0432346083],"iteration":270,"passed_time":3.998653685,"remaining_time":10.75652596},
{"learn":[0.04308633895],"iteration":271,"passed_time":4.017760683,"remaining_time":10.7534183},
{"learn":[0.04294195459],"iteration":272,"passed_time":4.03146155,"remaining_time":10.73579688},
{"learn":[0.04277926874],"iteration":273,"passed_time":4.04682324,"remaining_time":10.72260464},
{"learn":[0.04264326168],"iteration":274,"passed_time":4.063813793,"remaining_time":10.71369091},
{"learn":[0.04240700947],"iteration":275,"passed_time":4.077458369,"remaining_time":10.69594152},
{"learn":[0.04226623248],"iteration":276,"passed_time":4.090734156,"remaining_time":10.67725919},
{"learn":[0.04206129286],"iteration":277,"passed_time":4.103756944,"remaining_time":10.65795868},
{"learn":[0.04191757449],"iteration":278,"passed_time":4.117045064,"remaining_time":10.63938886},
{"learn":[0.04179650691],"iteration":279,"passed_time":4.134204991,"remaining_time":10.63081284},
{"learn":[0.04169237552],"iteration":280,"passed_time":4.150435508,"remaining_time":10.61979762},
{"learn":[0.04158240637],"iteration":281,"passed_time":4.166637526,"remaining_time":10.60867285},
{"learn":[0.04147410943],"iteration":282,"passed_time":4.179675106,"remaining_time":10.58949488},
{"learn":[0.04123920735],"iteration":283,"passed_time":4.192979434,"remaining_time":10.57103266},
{"learn":[0.04111741348],"iteration":284,"passed_time":4.208035417,"remaining_time":10.55700113},
{"learn":[0.040968664],"iteration":285,"passed_time":4.223538605,"remaining_time":10.5440789},
{"learn":[0.0409192323],"iteration":286,"passed_time":4.23987108,"remaining_time":10.53319889},
{"learn":[0.04080087376],"iteration":287,"passed_time":4.25440465,"remaining_time":10.51783372},
{"learn":[0.04066437932],"iteration":288,"passed_time":4.268357599,"remaining_time":10.50104586},
{"learn":[0.04054175564],"iteration":289,"passed_time":4.282451797,"remaining_time":10.48462336},
{"learn":[0.04030783286],"iteration":290,"passed_time":4.295894624,"remaining_time":10.46662986},
{"learn":[0.04004887219],"iteration":291,"passed_time":4.31177106,"remaining_time":10.45456819},
{"learn":[0.03987253617],"iteration":292,"passed_time":4.329696357,"remaining_time":10.44742432},
{"learn":[0.03973064832],"iteration":293,"passed_time":4.342990269,"remaining_time":10.42908548},
{"learn":[0.03965233335],"iteration":294,"passed_time":4.358450583,"remaining_time":10.41595817},
{"learn":[0.03946359158],"iteration":295,"passed_time":4.37158712,"remaining_time":10.39728829},
{"learn":[0.03934797624],"iteration":296,"passed_time":4.385157822,"remaining_time":10.37968333},
{"learn":[0.03924212965],"iteration":297,"passed_time":4.399255811,"remaining_time":10.36334758},
{"learn":[0.03908318718],"iteration":298,"passed_time":4.414739958,"remaining_time":10.35027662},
{"learn":[0.03889565908],"iteration":299,"passed_time":4.4322483,"remaining_time":10.3419127},
{"learn":[0.03880239903],"iteration":300,"passed_time":4.45030443,"remaining_time":10.33476012},
{"learn":[0.03868117068],"iteration":301,"passed_time":4.464784583,"remaining_time":10.31927033},
{"learn":[0.0385868182],"iteration":302,"passed_time":4.481291265,"remaining_time":10.30844888},
{"learn":[0.03843588421],"iteration":303,"passed_time":4.498043362,"remaining_time":10.29815191},
{"learn":[0.03834790784],"iteration":304,"passed_time":4.511056109,"remaining_time":10.27929179},
{"learn":[0.03824474276],"iteration":305,"passed_time":4.525473138,"remaining_time":10.26365476},
{"learn":[0.03799194814],"iteration":306,"passed_time":4.540438247,"remaining_time":10.24926288},
{"learn":[0.03789089455],"iteration":307,"passed_time":4.55927633,"remaining_time":10.2435689},
{"learn":[0.0378159587],"iteration":308,"passed_time":4.577419209,"remaining_time":10.23623519},
{"learn":[0.03771833081],"iteration":309,"passed_time":4.590675496,"remaining_time":10.21795514},
{"learn":[0.03756775853],"iteration":310,"passed_time":4.60835092,"remaining_time":10.2094977},
{"learn":[0.03744522274],"iteration":311,"passed_time":4.622110828,"remaining_time":10.19234695},
{"learn":[0.03725987955],"iteration":312,"passed_time":4.635377407,"remaining_time":10.17413507},
{"learn":[0.03710873021],"iteration":313,"passed_time":4.652131837,"remaining_time":10.16357465},
{"learn":[0.03702726232],"iteration":314,"passed_time":4.667494985,"remaining_time":10.14994941},
{"learn":[0.03691487976],"iteration":315,"passed_time":4.684424914,"remaining_time":10.13970456},
{"learn":[0.03683311806],"iteration":316,"passed_time":4.700885429,"remaining_time":10.12840615},
{"learn":[0.0367325847],"iteration":317,"passed_time":4.714810253,"remaining_time":10.11163708},
{"learn":[0.03656981474],"iteration":318,"passed_time":4.729428281,"remaining_time":10.0963657},
{"learn":[0.03648851482],"iteration":319,"passed_time":4.742254487,"remaining_time":10.07729079},
{"learn":[0.03637952253],"iteration":320,"passed_time":4.756513934,"remaining_time":10.06128648},
{"learn":[0.03621341506],"iteration":321,"passed_time":4.76885831,"remaining_time":10.04126067},
{"learn":[0.0361500443],"iteration":322,"passed_time":4.787564686,"remaining_time":10.034617},
{"learn":[0.035987872],"iteration":323,"passed_time":4.805597399,"remaining_time":10.02649334},
{"learn":[0.0358694917],"iteration":324,"passed_time":4.821733042,"remaining_time":10.01436863},
{"learn":[0.03584887087],"iteration":325,"passed_time":4.836089488,"remaining_time":9.998540843},
{"learn":[0.0357331928],"iteration":326,"passed_time":4.854543865,"remaining_time":9.991156028},
{"learn":[0.03561774343],"iteration":327,"passed_time":4.870529009,"remaining_time":9.978644798},
{"learn":[0.03560263],"iteration":328,"passed_time":4.889418925,"remaining_time":9.972036773},
{"learn":[0.03554504994],"iteration":329,"passed_time":4.902939543,"remaining_time":9.954453012},
{"learn":[0.03551253933],"iteration":330,"passed_time":4.919991221,"remaining_time":9.944030595},
{"learn":[0.03538026838],"iteration":331,"passed_time":4.933359799,"remaining_time":9.926157668},
{"learn":[0.0352524812],"iteration":332,"passed_time":4.953524915,"remaining_time":9.92192528},
{"learn":[0.03497925351],"iteration":333,"passed_time":4.96974614,"remaining_time":9.909733321},
{"learn":[0.03491653381],"iteration":334,"passed_time":4.983412049,"remaining_time":9.892444814},
{"learn":[0.03478709022],"iteration":335,"passed_time":4.996432671,"remaining_time":9.873902659},
{"learn":[0.0347161341],"iteration":336,"passed_time":5.0107822,"remaining_time":9.858007712},
{"learn":[0.03461426862],"iteration":337,"passed_time":5.025301896,"remaining_time":9.842455192},
{"learn":[0.03458884981],"iteration":338,"passed_time":5.041666412,"remaining_time":9.830505894},
{"learn":[0.03444003424],"iteration":339,"passed_time":5.05468995,"remaining_time":9.812045197},
{"learn":[0.03433282909],"iteration":340,"passed_time":5.070208847,"remaining_time":9.798438798},
{"learn":[0.03417802563],"iteration":341,"passed_time":5.082345099,"remaining_time":9.778313086},
{"learn":[0.03405798692],"iteration":342,"passed_time":5.094561101,"remaining_time":9.758386716},
{"learn":[0.03392343919],"iteration":343,"passed_time":5.108423551,"remaining_time":9.741644911},
{"learn":[0.03383570255],"iteration":344,"passed_time":5.123121578,"remaining_time":9.726506184},
{"learn":[0.03379104868],"iteration":345,"passed_time":5.140995792,"remaining_time":9.71737355},
{"learn":[0.0336411647],"iteration":346,"passed_time":5.156003859,"remaining_time":9.702796888},
{"learn":[0.03358842374],"iteration":347,"passed_time":5.173113537,"remaining_time":9.692155247},
{"learn":[0.03348544685],"iteration":348,"passed_time":5.188808724,"remaining_time":9.67883805},
{"learn":[0.03341637732],"iteration":349,"passed_time":5.204864242,"remaining_time":9.66617645},
{"learn":[0.03325616904],"iteration":350,"passed_time":5.220780678,"remaining_time":9.653238348},
{"learn":[0.03311623308],"iteration":351,"passed_time":5.235541872,"remaining_time":9.638156627},
{"learn":[0.03303969248],"iteration":352,"passed_time":5.248410453,"remaining_time":9.619607827},
{"learn":[0.03292866852],"iteration":353,"passed_time":5.263212229,"remaining_time":9.604618927},
{"learn":[0.03281774359],"iteration":354,"passed_time":5.281007319,"remaining_time":9.595069636},
{"learn":[0.0327307687],"iteration":355,"passed_time":5.293756318,"remaining_time":9.576345698},
{"learn":[0.03265742462],"iteration":356,"passed_time":5.311751406,"remaining_time":9.567104073},
{"learn":[0.03252884237],"iteration":357,"passed_time":5.324742903,"remaining_time":9.548840625},
{"learn":[0.03245894489],"iteration":358,"passed_time":5.340631422,"remaining_time":9.535779225},
{"learn":[0.03233502198],"iteration":359,"passed_time":5.353173256,"remaining_time":9.516752454},
{"learn":[0.03219689062],"iteration":360,"passed_time":5.365924004,"remaining_time":9.498131409},
{"learn":[0.03205552933],"iteration":361,"passed_time":5.3815604,"remaining_time":9.48462855},
{"learn":[0.03191752353],"iteration":362,"passed_time":5.39783275,"remaining_time":9.472229922},
{"learn":[0.03191183401],"iteration":363,"passed_time":5.417908116,"remaining_time":9.466454841},
{"learn":[0.03186361111],"iteration":364,"passed_time":5.43321789,"remaining_time":9.452310575},
{"learn":[0.03175668334],"iteration":365,"passed_time":5.448679787,"remaining_time":9.438423456},
{"learn":[0.03163886522],"iteration":366,"passed_time":5.466913374,"remaining_time":9.429308353},
{"learn":[0.03154453164],"iteration":367,"passed_time":5.484246342,"remaining_time":9.418596978},
{"learn":[0.03141530647],"iteration":368,"passed_time":5.499131451,"remaining_time":9.403663809},
{"learn":[0.03130330972],"iteration":369,"passed_time":5.513867978,"remaining_time":9.388477908},
{"learn":[0.03114032453],"iteration":370,"passed_time":5.526412061,"remaining_time":9.369577322},
{"learn":[0.03103727749],"iteration":371,"passed_time":5.539688473,"remaining_time":9.351947207},
{"learn":[0.0309311607],"iteration":372,"passed_time":5.554245834,"remaining_time":9.336493668},
{"learn":[0.03087803106],"iteration":373,"passed_time":5.568098742,"remaining_time":9.319865809},
{"learn":[0.03083468829],"iteration":374,"passed_time":5.58543896,"remaining_time":9.309064933},
{"learn":[0.03070609346],"iteration":375,"passed_time":5.597558088,"remaining_time":9.289564486},
{"learn":[0.03061012798],"iteration":376,"passed_time":5.610858333,"remaining_time":9.272055017},
{"learn":[0.03051414186],"iteration":377,"passed_time":5.625635401,"remaining_time":9.256997935},
{"learn":[0.03044513808],"iteration":378,"passed_time":5.642248874,"remaining_time":9.244951321},
{"learn":[0.03039597826],"iteration":379,"passed_time":5.65890168,"remaining_time":9.232944846},
{"learn":[0.03029424316],"iteration":380,"passed_time":5.672067009,"remaining_time":9.215247975},
{"learn":[0.03021595832],"iteration":381,"passed_time":5.686361455,"remaining_time":9.199401517},
{"learn":[0.03015089346],"iteration":382,"passed_time":5.6996867,"remaining_time":9.182001812},
{"learn":[0.03010847516],"iteration":383,"passed_time":5.7133879,"remaining_time":9.165226424},
{"learn":[0.03002337373],"iteration":384,"passed_time":5.727307058,"remaining_time":9.14881517},
{"learn":[0.02988942747],"iteration":385,"passed_time":5.741388214,"remaining_time":9.132674517},
{"learn":[0.02980888715],"iteration":386,"passed_time":5.757704231,"remaining_time":9.120084479},
{"learn":[0.02978630899],"iteration":387,"passed_time":5.776319607,"remaining_time":9.11110206},
{"learn":[0.02966653147],"iteration":388,"passed_time":5.79092151,"remaining_time":9.095766176},
{"learn":[0.02960607429],"iteration":389,"passed_time":5.805983201,"remaining_time":9.081153212},
{"learn":[0.02944682177],"iteration":390,"passed_time":5.817723373,"remaining_time":9.061364537},
{"learn":[0.0293252249],"iteration":391,"passed_time":5.835370255,"remaining_time":9.050778355},
{"learn":[0.02923147606],"iteration":392,"passed_time":5.848694,"remaining_time":9.033479028},
{"learn":[0.02905179499],"iteration":393,"passed_time":5.861837163,"remaining_time":9.015922133},
{"learn":[0.02896621252],"iteration":394,"passed_time":5.878052763,"remaining_time":9.003093473},
{"learn":[0.02882725154],"iteration":395,"passed_time":5.890550888,"remaining_time":8.984577617},
{"learn":[0.02872825832],"iteration":396,"passed_time":5.905649579,"remaining_time":8.970042056},
{"learn":[0.02859496452],"iteration":397,"passed_time":5.91888195,"remaining_time":8.952680738},
{"learn":[0.02847344712],"iteration":398,"passed_time":5.933196729,"remaining_time":8.936970512},
{"learn":[0.02838287486],"iteration":399,"passed_time":5.946198393,"remaining_time":8.919297589},
{"learn":[0.02830700666],"iteration":400,"passed_time":5.959728511,"remaining_time":8.902437352},
{"learn":[0.02821586529],"iteration":401,"passed_time":5.974905494,"remaining_time":8.888043495},
{"learn":[0.02812481143],"iteration":402,"passed_time":5.988077031,"remaining_time":8.870674907},
{"learn":[0.02802137874],"iteration":403,"passed_time":6.002308436,"remaining_time":8.854890663},
{"learn":[0.02797289789],"iteration":404,"passed_time":6.018678661,"remaining_time":8.842256304},
{"learn":[0.02794331325],"iteration":405,"passed_time":6.034180099,"remaining_time":8.82833246},
{"learn":[0.02788725181],"iteration":406,"passed_time":6.049612788,"remaining_time":8.814300696},
{"learn":[0.02782231861],"iteration":407,"passed_time":6.062919533,"remaining_time":8.797177362},
{"learn":[0.02774436741],"iteration":408,"passed_time":6.079389007,"remaining_time":8.784642795},
{"learn":[0.02766469898],"iteration":409,"passed_time":6.091158095,"remaining_time":8.765325064},
{"learn":[0.02761164015],"iteration":410,"passed_time":6.104146134,"remaining_time":8.747790931},
{"learn":[0.02752507219],"iteration":411,"passed_time":6.120833273,"remaining_time":8.735558166},
{"learn":[0.02745905051],"iteration":412,"passed_time":6.135080803,"remaining_time":8.719836395},
{"learn":[0.02741655519],"iteration":413,"passed_time":6.151886733,"remaining_time":8.707743056},
{"learn":[0.02730500474],"iteration":414,"passed_time":6.165153186,"remaining_time":8.690637624},
{"learn":[0.02720262168],"iteration":415,"passed_time":6.181816575,"remaining_time":8.678319423},
{"learn":[0.02711689726],"iteration":416,"passed_time":6.197496638,"remaining_time":8.664605611},
{"learn":[0.02700878409],"iteration":417,"passed_time":6.212177415,"remaining_time":8.649491042},
{"learn":[0.02690531633],"iteration":418,"passed_time":6.225390702,"remaining_time":8.63234367},
{"learn":[0.02684612727],"iteration":419,"passed_time":6.240149562,"remaining_time":8.617349395},
{"learn":[0.02682546884],"iteration":420,"passed_time":6.260605968,"remaining_time":8.610192055},
{"learn":[0.02673192305],"iteration":421,"passed_time":6.273575673,"remaining_time":8.592717391},
{"learn":[0.02666240753],"iteration":422,"passed_time":6.286180256,"remaining_time":8.574765975},
{"learn":[0.02663077524],"iteration":423,"passed_time":6.301567278,"remaining_time":8.560619699},
{"learn":[0.02657410268],"iteration":424,"passed_time":6.316727344,"remaining_time":8.546160524},
{"learn":[0.0265157666],"iteration":425,"passed_time":6.330085047,"remaining_time":8.529269523},
{"learn":[0.02644836688],"iteration":426,"passed_time":6.345416153,"remaining_time":8.515043222},
{"learn":[0.02635240986],"iteration":427,"passed_time":6.358893272,"remaining_time":8.498333999},
{"learn":[0.02626656409],"iteration":428,"passed_time":6.373439175,"remaining_time":8.483062399},
{"learn":[0.02622616751],"iteration":429,"passed_time":6.38724525,"remaining_time":8.466813471},
{"learn":[0.02613429574],"iteration":430,"passed_time":6.401642113,"remaining_time":8.451355828},
{"learn":[0.02602978816],"iteration":431,"passed_time":6.413548658,"remaining_time":8.432628791},
{"learn":[0.02595755689],"iteration":432,"passed_time":6.425877826,"remaining_time":8.414486669},
{"learn":[0.02589432584],"iteration":433,"passed_time":6.439724567,"remaining_time":8.398350473},
{"learn":[0.02580798365],"iteration":434,"passed_time":6.454577594,"remaining_time":8.383531817},
{"learn":[0.02576554379],"iteration":435,"passed_time":6.468901582,"remaining_time":8.368028651},
{"learn":[0.02571231526],"iteration":436,"passed_time":6.484171105,"remaining_time":8.353749044},
{"learn":[0.02564401982],"iteration":437,"passed_time":6.499886125,"remaining_time":8.340036535},
{"learn":[0.02553636471],"iteration":438,"passed_time":6.514516403,"remaining_time":8.324928706},
{"learn":[0.02545027135],"iteration":439,"passed_time":6.527289568,"remaining_time":8.30745945},
{"learn":[0.02539188756],"iteration":440,"passed_time":6.543501919,"remaining_time":8.294370913},
{"learn":[0.0253113679],"iteration":441,"passed_time":6.556698497,"remaining_time":8.277460999},
{"learn":[0.02525185585],"iteration":442,"passed_time":6.572122686,"remaining_time":8.263368705},
{"learn":[0.02520283496],"iteration":443,"passed_time":6.585955428,"remaining_time":8.247277518},
{"learn":[0.02510528914],"iteration":444,"passed_time":6.598258763,"remaining_time":8.229289018},
{"learn":[0.02507288253],"iteration":445,"passed_time":6.613894492,"remaining_time":8.215465355},
{"learn":[0.02503120835],"iteration":446,"passed_time":6.628579852,"remaining_time":8.200457849},
{"learn":[0.02492378751],"iteration":447,"passed_time":6.644251665,"remaining_time":8.18666723},
{"learn":[0.0248570146],"iteration":448,"passed_time":6.656751873,"remaining_time":8.16897613},
{"learn":[0.02479093038],"iteration":449,"passed_time":6.66872121,"remaining_time":8.150659257},
{"learn":[0.02471691923],"iteration":450,"passed_time":6.684140608,"remaining_time":8.136570274},
{"learn":[0.02468773519],"iteration":451,"passed_time":6.700783497,"remaining_time":8.123958753},
{"learn":[0.02464044411],"iteration":452,"passed_time":6.719546206,"remaining_time":8.113889127},
{"learn":[0.02458681465],"iteration":453,"passed_time":6.735760681,"remaining_time":8.10071659},
{"learn":[0.02454353144],"iteration":454,"passed_time":6.749826421,"remaining_time":8.084956922},
{"learn":[0.02445823153],"iteration":455,"passed_time":6.766221228,"remaining_time":8.07198322},
{"learn":[0.02436836023],"iteration":456,"passed_time":6.781115421,"remaining_time":8.057211539},
{"learn":[0.02430714779],"iteration":457,"passed_time":6.79423,"remaining_time":8.040333319},
{"learn":[0.02424734871],"iteration":458,"passed_time":6.81009102,"remaining_time":8.026708588},
{"learn":[0.02418058267],"iteration":459,"passed_time":6.824076593,"remaining_time":8.010872523},
{"learn":[0.02415150442],"iteration":460,"passed_time":6.840051029,"remaining_time":7.997369858},
{"learn":[0.02408988296],"iteration":461,"passed_time":6.853946895,"remaining_time":7.981435994},
{"learn":[0.02396380475],"iteration":462,"passed_time":6.870659283,"remaining_time":7.968777614},
{"learn":[0.02390516803],"iteration":463,"passed_time":6.885729141,"remaining_time":7.954204353},
{"learn":[0.02386340806],"iteration":464,"passed_time":6.900781333,"remaining_time":7.93960863},
{"learn":[0.02381333281],"iteration":465,"passed_time":6.915713359,"remaining_time":7.924873248},
{"learn":[0.02372481985],"iteration":466,"passed_time":6.928275567,"remaining_time":7.907432285},
{"learn":[0.02367099743],"iteration":467,"passed_time":6.944266252,"remaining_time":7.8939095},
{"learn":[0.02363840626],"iteration":468,"passed_time":6.962444839,"remaining_time":7.882853326},
{"learn":[0.02359352086],"iteration":469,"passed_time":6.975287796,"remaining_time":7.865750067},
{"learn":[0.02352255124],"iteration":470,"passed_time":6.990539402,"remaining_time":7.851370157},
{"learn":[0.0234352021],"iteration":471,"passed_time":7.00599105,"remaining_time":7.837210327},
{"learn":[0.02337000319],"iteration":472,"passed_time":7.021823653,"remaining_time":7.823469482},
{"learn":[0.02327440593],"iteration":473,"passed_time":7.035464728,"remaining_time":7.807287863},
{"learn":[0.02322239356],"iteration":474,"passed_time":7.048017895,"remaining_time":7.789914515},
{"learn":[0.02315796938],"iteration":475,"passed_time":7.062333925,"remaining_time":7.774502052},
{"learn":[0.02303898033],"iteration":476,"passed_time":7.075668753,"remaining_time":7.75801836},
{"learn":[0.0229451346],"iteration":477,"passed_time":7.089771242,"remaining_time":7.742386168},
{"learn":[0.02281026613],"iteration":478,"passed_time":7.103187986,"remaining_time":7.72601449},
{"learn":[0.02276682809],"iteration":479,"passed_time":7.120231039,"remaining_time":7.713583626},
{"learn":[0.02269305476],"iteration":480,"passed_time":7.131958836,"remaining_time":7.695398412},
{"learn":[0.02262261859],"iteration":481,"passed_time":7.147385859,"remaining_time":7.681215508},
{"learn":[0.02254368432],"iteration":482,"passed_time":7.160112149,"remaining_time":7.664136607},
{"learn":[0.02250153941],"iteration":483,"passed_time":7.174693302,"remaining_time":7.64905319},
{"learn":[0.02240996647],"iteration":484,"passed_time":7.18723901,"remaining_time":7.631810495},
{"learn":[0.02236817676],"iteration":485,"passed_time":7.202092411,"remaining_time":7.617027777},
{"learn":[0.02229557609],"iteration":486,"passed_time":7.217231186,"remaining_time":7.602545376},
{"learn":[0.02222343623],"iteration":487,"passed_time":7.231243842,"remaining_time":7.586878785},
{"learn":[0.0221609899],"iteration":488,"passed_time":7.245159375,"remaining_time":7.571117465},
{"learn":[0.0221272951],"iteration":489,"passed_time":7.258585869,"remaining_time":7.55485468},
{"learn":[0.02198967845],"iteration":490,"passed_time":7.272101446,"remaining_time":7.538695796},
{"learn":[0.02194836672],"iteration":491,"passed_time":7.286509141,"remaining_time":7.523468788},
{"learn":[0.02187125684],"iteration":492,"passed_time":7.29942243,"remaining_time":7.50670826},
{"learn":[0.02179102701],"iteration":493,"passed_time":7.316737232,"remaining_time":7.49447174},
{"learn":[0.0217044318],"iteration":494,"passed_time":7.330270184,"remaining_time":7.47835645},
{"learn":[0.02165128147],"iteration":495,"passed_time":7.346004412,"remaining_time":7.464488354},
{"learn":[0.02159410393],"iteration":496,"passed_time":7.362326345,"remaining_time":7.451207549},
{"learn":[0.02156697253],"iteration":497,"passed_time":7.378380863,"remaining_time":7.437644967},
{"learn":[0.02150053757],"iteration":498,"passed_time":7.391419277,"remaining_time":7.421044204},
{"learn":[0.02146030569],"iteration":499,"passed_time":7.405494933,"remaining_time":7.405494933},
{"learn":[0.02144633336],"iteration":500,"passed_time":7.420338168,"remaining_time":7.390716059},
{"learn":[0.0213649903],"iteration":501,"passed_time":7.438036758,"remaining_time":7.378769533},
{"learn":[0.02128952409],"iteration":502,"passed_time":7.454492315,"remaining_time":7.36557193},
{"learn":[0.02128129704],"iteration":503,"passed_time":7.475725591,"remaining_time":7.35706328},
{"learn":[0.02125612293],"iteration":504,"passed_time":7.488967628,"remaining_time":7.340671239},
{"learn":[0.02115161792],"iteration":505,"passed_time":7.502001249,"remaining_time":7.324088176},
{"learn":[0.02109518611],"iteration":506,"passed_time":7.516265071,"remaining_time":7.308715345},
{"learn":[0.0210521112],"iteration":507,"passed_time":7.530168562,"remaining_time":7.292997898},
{"learn":[0.02099088837],"iteration":508,"passed_time":7.546287496,"remaining_time":7.279424677},
{"learn":[0.02094076269],"iteration":509,"passed_time":7.564517708,"remaining_time":7.267869955},
{"learn":[0.02090093762],"iteration":510,"passed_time":7.58020377,"remaining_time":7.253854489},
{"learn":[0.02085968753],"iteration":511,"passed_time":7.593149226,"remaining_time":7.237220356},
{"learn":[0.02081121228],"iteration":512,"passed_time":7.611643936,"remaining_time":7.22586861},
{"learn":[0.0207882214],"iteration":513,"passed_time":7.626838794,"remaining_time":7.211368976},
{"learn":[0.02074751862],"iteration":514,"passed_time":7.641530654,"remaining_time":7.196392946},
{"learn":[0.02068221838],"iteration":515,"passed_time":7.658093336,"remaining_time":7.183172819},
{"learn":[0.02064280249],"iteration":516,"passed_time":7.675363346,"remaining_time":7.170600572},
{"learn":[0.02061844438],"iteration":517,"passed_time":7.691672945,"remaining_time":7.157116525},
{"learn":[0.02059283558],"iteration":518,"passed_time":7.707387383,"remaining_time":7.143070002},
{"learn":[0.02055888447],"iteration":519,"passed_time":7.723426692,"remaining_time":7.129316947},
{"learn":[0.02051984906],"iteration":520,"passed_time":7.737218976,"remaining_time":7.113489231},
{"learn":[0.02047482759],"iteration":521,"passed_time":7.750019599,"remaining_time":7.096761242},
{"learn":[0.02039563343],"iteration":522,"passed_time":7.766294574,"remaining_time":7.08321704},
{"learn":[0.0203442814],"iteration":523,"passed_time":7.782831922,"remaining_time":7.069900754},
{"learn":[0.02027602621],"iteration":524,"passed_time":7.796310249,"remaining_time":7.053804511},
{"learn":[0.02020950149],"iteration":525,"passed_time":7.810802611,"remaining_time":7.038632011},
{"learn":[0.02012696409],"iteration":526,"passed_time":7.824473812,"remaining_time":7.022725072},
{"learn":[0.02008531381],"iteration":527,"passed_time":7.83953617,"remaining_time":7.008070212},
{"learn":[0.02004847884],"iteration":528,"passed_time":7.853595076,"remaining_time":6.99252038},
{"learn":[0.0200235825],"iteration":529,"passed_time":7.87160179,"remaining_time":6.980477059},
{"learn":[0.01999573269],"iteration":530,"passed_time":7.887049937,"remaining_time":6.966151451},
{"learn":[0.0199266242],"iteration":531,"passed_time":7.905979769,"remaining_time":6.954884459},
{"learn":[0.01986875145],"iteration":532,"passed_time":7.920244925,"remaining_time":6.939501651},
{"learn":[0.01981866105],"iteration":533,"passed_time":7.935634905,"remaining_time":6.925104618},
{"learn":[0.01975740731],"iteration":534,"passed_time":7.948783526,"remaining_time":6.908755775},
{"learn":[0.01973819382],"iteration":535,"passed_time":7.965277042,"remaining_time":6.895314454},
{"learn":[0.01969369766],"iteration":536,"passed_time":7.978444662,"remaining_time":6.878994187},
{"learn":[0.01962769733],"iteration":537,"passed_time":7.991475284,"remaining_time":6.862567995},
{"learn":[0.01958840805],"iteration":538,"passed_time":8.007853217,"remaining_time":6.849017315},
{"learn":[0.01954349139],"iteration":539,"passed_time":8.021618708,"remaining_time":6.833230752},
{"learn":[0.01951042402],"iteration":540,"passed_time":8.035648657,"remaining_time":6.817676032},
{"learn":[0.01949489801],"iteration":541,"passed_time":8.050754514,"remaining_time":6.803036103},
{"learn":[0.01946335556],"iteration":542,"passed_time":8.065735373,"remaining_time":6.788289255},
{"learn":[0.01943333681],"iteration":543,"passed_time":8.078417039,"remaining_time":6.771614282},
{"learn":[0.01939614067],"iteration":544,"passed_time":8.097210955,"remaining_time":6.760056853},
{"learn":[0.01934857206],"iteration":545,"passed_time":8.109870079,"remaining_time":6.743371824},
{"learn":[0.0193067698],"iteration":546,"passed_time":8.123282824,"remaining_time":6.727325629},
{"learn":[0.01929789618],"iteration":547,"passed_time":8.14085454,"remaining_time":6.714719438},
{"learn":[0.01927991635],"iteration":548,"passed_time":8.155806524,"remaining_time":6.699943064},
{"learn":[0.01925577915],"iteration":549,"passed_time":8.171672252,"remaining_time":6.68591366},
{"learn":[0.01921514832],"iteration":550,"passed_time":8.185128829,"remaining_time":6.669914418},
{"learn":[0.01918751896],"iteration":551,"passed_time":8.200039771,"remaining_time":6.655104742},
{"learn":[0.01913365387],"iteration":552,"passed_time":8.213396141,"remaining_time":6.63903811},
{"learn":[0.01909340406],"iteration":553,"passed_time":8.225756058,"remaining_time":6.622179065},
{"learn":[0.0190311806],"iteration":554,"passed_time":8.239894923,"remaining_time":6.606762596},
{"learn":[0.01897517549],"iteration":555,"passed_time":8.254977156,"remaining_time":6.59210406},
{"learn":[0.01891725682],"iteration":556,"passed_time":8.271808502,"remaining_time":6.578835128},
{"learn":[0.01886991131],"iteration":557,"passed_time":8.287233899,"remaining_time":6.564439755},
{"learn":[0.01881255627],"iteration":558,"passed_time":8.300002356,"remaining_time":6.547944614},
{"learn":[0.01877391769],"iteration":559,"passed_time":8.31536067,"remaining_time":6.53349767},
{"learn":[0.01873030832],"iteration":560,"passed_time":8.329085079,"remaining_time":6.517768894},
{"learn":[0.01868288741],"iteration":561,"passed_time":8.342062576,"remaining_time":6.501465139},
{"learn":[0.018674008],"iteration":562,"passed_time":8.357668014,"remaining_time":6.487213006},
{"learn":[0.01863308993],"iteration":563,"passed_time":8.372739497,"remaining_time":6.472543299},
{"learn":[0.01861012649],"iteration":564,"passed_time":8.386958027,"remaining_time":6.457215472},
{"learn":[0.0185668367],"iteration":565,"passed_time":8.402267676,"remaining_time":6.442728218},
{"learn":[0.01849830046],"iteration":566,"passed_time":8.417847489,"remaining_time":6.428444378},
{"learn":[0.01844074871],"iteration":567,"passed_time":8.433204595,"remaining_time":6.413986593},
{"learn":[0.01840791586],"iteration":568,"passed_time":8.44695592,"remaining_time":6.398309317},
{"learn":[0.01835437192],"iteration":569,"passed_time":8.465458297,"remaining_time":6.386222926},
{"learn":[0.0183009386],"iteration":570,"passed_time":8.477578716,"remaining_time":6.369319211},
{"learn":[0.01828468456],"iteration":571,"passed_time":8.49696917,"remaining_time":6.357872037},
{"learn":[0.01823044924],"iteration":572,"passed_time":8.509477462,"remaining_time":6.341268545},
{"learn":[0.01813931316],"iteration":573,"passed_time":8.527103553,"remaining_time":6.32847755},
{"learn":[0.0180859517],"iteration":574,"passed_time":8.5425677,"remaining_time":6.314071779},
{"learn":[0.01804731469],"iteration":575,"passed_time":8.554957118,"remaining_time":6.29739899},
{"learn":[0.01801203417],"iteration":576,"passed_time":8.570337057,"remaining_time":6.282933406},
{"learn":[0.01797780683],"iteration":577,"passed_time":8.585076584,"remaining_time":6.267997091},
{"learn":[0.01792742392],"iteration":578,"passed_time":8.601889014,"remaining_time":6.254568696},
{"learn":[0.01787044509],"iteration":579,"passed_time":8.618394196,"remaining_time":6.240906142},
{"learn":[0.01783518703],"iteration":580,"passed_time":8.634371173,"remaining_time":6.226852877},
{"learn":[0.01779467826],"iteration":581,"passed_time":8.650246859,"remaining_time":6.212720253},
{"learn":[0.01771853762],"iteration":582,"passed_time":8.663952518,"remaining_time":6.197029502},
{"learn":[0.01766648473],"iteration":583,"passed_time":8.677010264,"remaining_time":6.180884024},
{"learn":[0.01763055439],"iteration":584,"passed_time":8.693417947,"remaining_time":6.167125552},
{"learn":[0.01757144509],"iteration":585,"passed_time":8.7092273,"remaining_time":6.152935328},
{"learn":[0.01755294316],"iteration":586,"passed_time":8.725349151,"remaining_time":6.138959454},
{"learn":[0.0174966978],"iteration":587,"passed_time":8.738806645,"remaining_time":6.123109418},
{"learn":[0.01748022097],"iteration":588,"passed_time":8.754549707,"remaining_time":6.108862359},
{"learn":[0.01743666753],"iteration":589,"passed_time":8.768903903,"remaining_time":6.093645085},
{"learn":[0.01737665199],"iteration":590,"passed_time":8.788247649,"remaining_time":6.081883737},
{"learn":[0.01734891256],"iteration":591,"passed_time":8.805155953,"remaining_time":6.068418292},
{"learn":[0.01732416874],"iteration":592,"passed_time":8.819071486,"remaining_time":6.052887175},
{"learn":[0.01723944512],"iteration":593,"passed_time":8.832755144,"remaining_time":6.037203011},
{"learn":[0.01720373743],"iteration":594,"passed_time":8.848351207,"remaining_time":6.022827292},
{"learn":[0.01715281257],"iteration":595,"passed_time":8.860842958,"remaining_time":6.006343213},
{"learn":[0.01711565808],"iteration":596,"passed_time":8.875288278,"remaining_time":5.99119125},
{"learn":[0.01707597082],"iteration":597,"passed_time":8.892000459,"remaining_time":5.977565526},
{"learn":[0.01703565953],"iteration":598,"passed_time":8.908716931,"remaining_time":5.963932369},
{"learn":[0.01698725053],"iteration":599,"passed_time":8.92265463,"remaining_time":5.94843642},
{"learn":[0.01694332753],"iteration":600,"passed_time":8.940283304,"remaining_time":5.93539607},
{"learn":[0.01694332238],"iteration":601,"passed_time":8.948987871,"remaining_time":5.916440486},
{"learn":[0.01691743997],"iteration":602,"passed_time":8.965199305,"remaining_time":5.902461234},
{"learn":[0.01687265337],"iteration":603,"passed_time":8.981022866,"remaining_time":5.88822029},
{"learn":[0.01681387427],"iteration":604,"passed_time":8.995833101,"remaining_time":5.873312521},
{"learn":[0.01679145225],"iteration":605,"passed_time":9.012195367,"remaining_time":5.85941415},
{"learn":[0.01676742606],"iteration":606,"passed_time":9.026987477,"remaining_time":5.844491068},
{"learn":[0.01672492741],"iteration":607,"passed_time":9.043486409,"remaining_time":5.830668869},
{"learn":[0.01670208099],"iteration":608,"passed_time":9.060441963,"remaining_time":5.817131047},
{"learn":[0.01663876837],"iteration":609,"passed_time":9.07882859,"remaining_time":5.804496968},
{"learn":[0.0165969423],"iteration":610,"passed_time":9.092046336,"remaining_time":5.788553232},
{"learn":[0.0165514465],"iteration":611,"passed_time":9.106353199,"remaining_time":5.773308891},
{"learn":[0.01652716173],"iteration":612,"passed_time":9.123914332,"remaining_time":5.760122099},
{"learn":[0.01649513788],"iteration":613,"passed_time":9.136919037,"remaining_time":5.744056593},
{"learn":[0.01647954132],"iteration":614,"passed_time":9.152608516,"remaining_time":5.729681754},
{"learn":[0.01642497556],"iteration":615,"passed_time":9.165479139,"remaining_time":5.713545437},
{"learn":[0.01639531181],"iteration":616,"passed_time":9.181240117,"remaining_time":5.699213882},
{"learn":[0.01636900431],"iteration":617,"passed_time":9.196471849,"remaining_time":5.684550561},
{"learn":[0.01631449656],"iteration":618,"passed_time":9.21035284,"remaining_time":5.66905401},
{"learn":[0.01627051959],"iteration":619,"passed_time":9.222823966,"remaining_time":5.65269856},
{"learn":[0.01622642684],"iteration":620,"passed_time":9.236767415,"remaining_time":5.637254187},
{"learn":[0.01620103174],"iteration":621,"passed_time":9.249887244,"remaining_time":5.621314113},
{"learn":[0.0161340562],"iteration":622,"passed_time":9.265349266,"remaining_time":5.606800439},
{"learn":[0.01610527086],"iteration":623,"passed_time":9.282502944,"remaining_time":5.593303056},
{"learn":[0.016076098],"iteration":624,"passed_time":9.295070152,"remaining_time":5.577042091},
{"learn":[0.01604451034],"iteration":625,"passed_time":9.308728019,"remaining_time":5.561444535},
{"learn":[0.0160349465],"iteration":626,"passed_time":9.327090147,"remaining_time":5.548651714},
{"learn":[0.01601479452],"iteration":627,"passed_time":9.344856445,"remaining_time":5.535488213},
{"learn":[0.01596085789],"iteration":628,"passed_time":9.359857929,"remaining_time":5.520679319},
{"learn":[0.01595448169],"iteration":629,"passed_time":9.371467143,"remaining_time":5.503877529},
{"learn":[0.0159348007],"iteration":630,"passed_time":9.387650369,"remaining_time":5.489767014},
{"learn":[0.01590776667],"iteration":631,"passed_time":9.400680366,"remaining_time":5.473813884},
{"learn":[0.01589706762],"iteration":632,"passed_time":9.416999549,"remaining_time":5.459776989},
{"learn":[0.015882595],"iteration":633,"passed_time":9.432244572,"remaining_time":5.445112797},
{"learn":[0.0158319605],"iteration":634,"passed_time":9.445509192,"remaining_time":5.429308433},
{"learn":[0.01579649603],"iteration":635,"passed_time":9.457645903,"remaining_time":5.412866523},
{"learn":[0.01577451127],"iteration":636,"passed_time":9.472022266,"remaining_time":5.397714415},
{"learn":[0.01573266417],"iteration":637,"passed_time":9.490022896,"remaining_time":5.384621142},
{"learn":[0.01569696694],"iteration":638,"passed_time":9.503869471,"remaining_time":5.369165695},
{"learn":[0.01562790811],"iteration":639,"passed_time":9.516938467,"remaining_time":5.353277888},
{"learn":[0.0156072256],"iteration":640,"passed_time":9.533375274,"remaining_time":5.33928506},
{"learn":[0.01557598078],"iteration":641,"passed_time":9.551296655,"remaining_time":5.326112465},
{"learn":[0.01551929905],"iteration":642,"passed_time":9.568468957,"remaining_time":5.312509203},
{"learn":[0.01547090772],"iteration":643,"passed_time":9.581620037,"remaining_time":5.296671946},
{"learn":[0.01543422082],"iteration":644,"passed_time":9.597786971,"remaining_time":5.282502906},
{"learn":[0.0154228156],"iteration":645,"passed_time":9.617714796,"remaining_time":5.270388604},
{"learn":[0.01540049299],"iteration":646,"passed_time":9.632881821,"remaining_time":5.255652678},
{"learn":[0.01537042971],"iteration":647,"passed_time":9.649923999,"remaining_time":5.241934024},
{"learn":[0.01534092298],"iteration":648,"passed_time":9.662868454,"remaining_time":5.225988948},
{"learn":[0.01528289582],"iteration":649,"passed_time":9.677338191,"remaining_time":5.210874411},
{"learn":[0.01525279216],"iteration":650,"passed_time":9.689240529,"remaining_time":5.194385476},
{"learn":[0.01520460826],"iteration":651,"passed_time":9.703544725,"remaining_time":5.179192583},
{"learn":[0.01517097852],"iteration":652,"passed_time":9.718605333,"remaining_time":5.164404366},
{"learn":[0.01514602448],"iteration":653,"passed_time":9.732943196,"remaining_time":5.149232945},
{"learn":[0.01511490235],"iteration":654,"passed_time":9.748773091,"remaining_time":5.134849949},
{"learn":[0.01509922059],"iteration":655,"passed_time":9.761656172,"remaining_time":5.118917261},
{"learn":[0.0150601151],"iteration":656,"passed_time":9.776915654,"remaining_time":5.104234504},
{"learn":[0.01501483343],"iteration":657,"passed_time":9.791390182,"remaining_time":5.08914201},
{"learn":[0.01497351613],"iteration":658,"passed_time":9.806164501,"remaining_time":5.074206517},
{"learn":[0.0149486324],"iteration":659,"passed_time":9.820612655,"remaining_time":5.059103489},
{"learn":[0.01491241513],"iteration":660,"passed_time":9.83663709,"remaining_time":5.044810852},
{"learn":[0.01486713661],"iteration":661,"passed_time":9.851112202,"remaining_time":5.02972194},
{"learn":[0.01483421106],"iteration":662,"passed_time":9.864103782,"remaining_time":5.013880806},
{"learn":[0.01481186003],"iteration":663,"passed_time":9.879759011,"remaining_time":4.999396126},
{"learn":[0.0147981191],"iteration":664,"passed_time":9.895496531,"remaining_time":4.984949381},
{"learn":[0.01476574402],"iteration":665,"passed_time":9.910179684,"remaining_time":4.969969992},
{"learn":[0.01474764883],"iteration":666,"passed_time":9.924476005,"remaining_time":4.954798365},
{"learn":[0.01471219871],"iteration":667,"passed_time":9.937649126,"remaining_time":4.939071122},
{"learn":[0.01469530973],"iteration":668,"passed_time":9.95200503,"remaining_time":4.923936719},
{"learn":[0.01465197456],"iteration":669,"passed_time":9.965466566,"remaining_time":4.908364129},
{"learn":[0.01462127631],"iteration":670,"passed_time":9.978416313,"remaining_time":4.892546896},
{"learn":[0.01458304661],"iteration":671,"passed_time":9.991855474,"remaining_time":4.876977076},
{"learn":[0.01454746539],"iteration":672,"passed_time":10.00430072,"remaining_time":4.860930664},
{"learn":[0.01451069059],"iteration":673,"passed_time":10.01819613,"remaining_time":4.845596349},
{"learn":[0.01448119822],"iteration":674,"passed_time":10.03473815,"remaining_time":4.831540589},
{"learn":[0.01446188712],"iteration":675,"passed_time":10.05071429,"remaining_time":4.817206257},
{"learn":[0.01442125866],"iteration":676,"passed_time":10.06376725,"remaining_time":4.801472408},
{"learn":[0.01442114722],"iteration":677,"passed_time":10.07224906,"remaining_time":4.783575514},
{"learn":[0.01438172916],"iteration":678,"passed_time":10.08588485,"remaining_time":4.76814291},
{"learn":[0.01435851226],"iteration":679,"passed_time":10.10156662,"remaining_time":4.753678409},
{"learn":[0.01432668052],"iteration":680,"passed_time":10.11358371,"remaining_time":4.737493689},
{"learn":[0.01430910257],"iteration":681,"passed_time":10.12588408,"remaining_time":4.721453282},
{"learn":[0.01428038799],"iteration":682,"passed_time":10.14114898,"remaining_time":4.706799746},
{"learn":[0.014243134],"iteration":683,"passed_time":10.15426064,"remaining_time":4.691149654},
{"learn":[0.01423145474],"iteration":684,"passed_time":10.16879117,"remaining_time":4.676159444},
{"learn":[0.01419690985],"iteration":685,"passed_time":10.18197713,"remaining_time":4.660555127},
{"learn":[0.0141928715],"iteration":686,"passed_time":10.19377088,"remaining_time":4.64432356},
{"learn":[0.0141811438],"iteration":687,"passed_time":10.21046585,"remaining_time":4.630327538},
{"learn":[0.01415858754],"iteration":688,"passed_time":10.22697141,"remaining_time":4.616238183},
{"learn":[0.0141348662],"iteration":689,"passed_time":10.24278189,"remaining_time":4.601829544},
{"learn":[0.01409000403],"iteration":690,"passed_time":10.25660355,"remaining_time":4.58652749},
{"learn":[0.01405933872],"iteration":691,"passed_time":10.26885342,"remaining_time":4.570530136},
{"learn":[0.01405932587],"iteration":692,"passed_time":10.28049172,"remaining_time":4.554272667},
{"learn":[0.01403735288],"iteration":693,"passed_time":10.29595016,"remaining_time":4.539712894},
{"learn":[0.01403619148],"iteration":694,"passed_time":10.30840037,"remaining_time":4.523830377},
{"learn":[0.01401258135],"iteration":695,"passed_time":10.32229282,"remaining_time":4.508587667},
{"learn":[0.01401242054],"iteration":696,"passed_time":10.33049701,"remaining_time":4.490876032},
{"learn":[0.01397629497],"iteration":697,"passed_time":10.34701299,"remaining_time":4.476787853},
{"learn":[0.01397629133],"iteration":698,"passed_time":10.35495881,"remaining_time":4.459002291},
{"learn":[0.01395682573],"iteration":699,"passed_time":10.36941096,"remaining_time":4.444033269},
{"learn":[0.01389803602],"iteration":700,"passed_time":10.3838002,"remaining_time":4.429038887},
{"learn":[0.01387176485],"iteration":701,"passed_time":10.40053446,"remaining_time":4.415041695},
{"learn":[0.01384428772],"iteration":702,"passed_time":10.4143725,"remaining_time":4.399813131},
{"learn":[0.01380521817],"iteration":703,"passed_time":10.43067193,"remaining_time":4.385623425},
{"learn":[0.01378451632],"iteration":704,"passed_time":10.44516008,"remaining_time":4.370669822},
{"learn":[0.01377720894],"iteration":705,"passed_time":10.46213151,"remaining_time":4.356751649},
{"learn":[0.01374958827],"iteration":706,"passed_time":10.47536871,"remaining_time":4.341277275},
{"learn":[0.01371792437],"iteration":707,"passed_time":10.48878213,"remaining_time":4.325881894},
{"learn":[0.01368066717],"iteration":708,"passed_time":10.50251153,"remaining_time":4.3106218},
{"learn":[0.01366136791],"iteration":709,"passed_time":10.51761781,"remaining_time":4.295928401},
{"learn":[0.01363412906],"iteration":710,"passed_time":10.53206775,"remaining_time":4.280967062},
{"learn":[0.0136317076],"iteration":711,"passed_time":10.54494334,"remaining_time":4.265370338},
{"learn":[0.01360011786],"iteration":712,"passed_time":10.5601569,"remaining_time":4.250722343},
{"learn":[0.0135896483],"iteration":713,"passed_time":10.57659442,"remaining_time":4.236563029},
{"learn":[0.0135823701],"iteration":714,"passed_time":10.59068903,"remaining_time":4.22146346},
{"learn":[0.01355346512],"iteration":715,"passed_time":10.60609818,"remaining_time":4.206888104},
{"learn":[0.01354042012],"iteration":716,"passed_time":10.62111391,"remaining_time":4.192155142},
{"learn":[0.01351081329],"iteration":717,"passed_time":10.63741018,"remaining_time":4.177924332},
{"learn":[0.01349284667],"iteration":718,"passed_time":10.65333332,"remaining_time":4.163541952},
{"learn":[0.01346979477],"iteration":719,"passed_time":10.66743977,"remaining_time":4.148448799},
{"learn":[0.01343497331],"iteration":720,"passed_time":10.6808391,"remaining_time":4.133084755},
{"learn":[0.01340796358],"iteration":721,"passed_time":10.6961445,"remaining_time":4.118460069},
{"learn":[0.01334520126],"iteration":722,"passed_time":10.71009561,"remaining_time":4.103314639},
{"learn":[0.01331344194],"iteration":723,"passed_time":10.72504389,"remaining_time":4.088552642},
{"learn":[0.01329762164],"iteration":724,"passed_time":10.73833276,"remaining_time":4.073160701},
{"learn":[0.01327164337],"iteration":725,"passed_time":10.75200479,"remaining_time":4.057919163},
{"learn":[0.01325427558],"iteration":726,"passed_time":10.76520029,"remaining_time":4.042502996},
{"learn":[0.01322481402],"iteration":727,"passed_time":10.78372383,"remaining_time":4.029083629},
{"learn":[0.0131998661],"iteration":728,"passed_time":10.79789065,"remaining_time":4.014030681},
{"learn":[0.01318255291],"iteration":729,"passed_time":10.81143348,"remaining_time":3.998749369},
{"learn":[0.01316525664],"iteration":730,"passed_time":10.82856566,"remaining_time":3.984793655},
{"learn":[0.01314017402],"iteration":731,"passed_time":10.84288356,"remaining_time":3.969798899},
{"learn":[0.01308885917],"iteration":732,"passed_time":10.85793321,"remaining_time":3.955072534},
{"learn":[0.01305626519],"iteration":733,"passed_time":10.87131908,"remaining_time":3.939742337},
{"learn":[0.01302077537],"iteration":734,"passed_time":10.88669748,"remaining_time":3.925135825},
{"learn":[0.01298681541],"iteration":735,"passed_time":10.90078472,"remaining_time":3.910064083},
{"learn":[0.01295495689],"iteration":736,"passed_time":10.91477896,"remaining_time":3.894961826},
{"learn":[0.01293759054],"iteration":737,"passed_time":10.92987594,"remaining_time":3.88025406},
{"learn":[0.01288943782],"iteration":738,"passed_time":10.94343552,"remaining_time":3.86500226},
{"learn":[0.0128769553],"iteration":739,"passed_time":10.95636164,"remaining_time":3.849532468},
{"learn":[0.01284565926],"iteration":740,"passed_time":10.97156541,"remaining_time":3.834865644},
{"learn":[0.01283189944],"iteration":741,"passed_time":10.98717693,"remaining_time":3.82033915},
{"learn":[0.01281661725],"iteration":742,"passed_time":11.00637056,"remaining_time":3.807048766},
{"learn":[0.01278077693],"iteration":743,"passed_time":11.02007272,"remaining_time":3.791852977},
{"learn":[0.01274771147],"iteration":744,"passed_time":11.03645361,"remaining_time":3.77757808},
{"learn":[0.01270768346],"iteration":745,"passed_time":11.05134226,"remaining_time":3.762789455},
{"learn":[0.01268530918],"iteration":746,"passed_time":11.06335247,"remaining_time":3.747025669},
{"learn":[0.01265339123],"iteration":747,"passed_time":11.078159,"remaining_time":3.732213993},
{"learn":[0.01264359112],"iteration":748,"passed_time":11.09348006,"remaining_time":3.71757476},
{"learn":[0.01261743123],"iteration":749,"passed_time":11.10658122,"remaining_time":3.702193741},
{"learn":[0.01260094474],"iteration":750,"passed_time":11.12143275,"remaining_time":3.687399141},
{"learn":[0.01256023511],"iteration":751,"passed_time":11.13692556,"remaining_time":3.672815877},
{"learn":[0.01253835264],"iteration":752,"passed_time":11.15088543,"remaining_time":3.657727358},
{"learn":[0.01251900778],"iteration":753,"passed_time":11.1680224,"remaining_time":3.643678395},
{"learn":[0.01248941258],"iteration":754,"passed_time":11.18301096,"remaining_time":3.628924088},
{"learn":[0.01246779986],"iteration":755,"passed_time":11.19614525,"remaining_time":3.61357069},
{"learn":[0.01244150224],"iteration":756,"passed_time":11.21302593,"remaining_time":3.599425761},
{"learn":[0.01241102228],"iteration":757,"passed_time":11.22805516,"remaining_time":3.58468252},
{"learn":[0.01239296688],"iteration":758,"passed_time":11.24479076,"remaining_time":3.570480334},
{"learn":[0.01237334585],"iteration":759,"passed_time":11.25666185,"remaining_time":3.554735321},
{"learn":[0.01237332032],"iteration":760,"passed_time":11.26564125,"remaining_time":3.538092324},
{"learn":[0.01237331121],"iteration":761,"passed_time":11.27351378,"remaining_time":3.521123726},
{"learn":[0.01234047593],"iteration":762,"passed_time":11.28955355,"remaining_time":3.506715846},
{"learn":[0.01232032783],"iteration":763,"passed_time":11.30463424,"remaining_time":3.492007435},
{"learn":[0.01228435094],"iteration":764,"passed_time":11.31715636,"remaining_time":3.476512086},
{"learn":[0.0122632438],"iteration":765,"passed_time":11.33034932,"remaining_time":3.461229426},
{"learn":[0.01225231906],"iteration":766,"passed_time":11.34397035,"remaining_time":3.446082258},
{"learn":[0.01223470548],"iteration":767,"passed_time":11.35617773,"remaining_time":3.430512022},
{"learn":[0.01223322261],"iteration":768,"passed_time":11.37423411,"remaining_time":3.416707515},
{"learn":[0.01221636632],"iteration":769,"passed_time":11.38912151,"remaining_time":3.401945386},
{"learn":[0.01220814003],"iteration":770,"passed_time":11.40521544,"remaining_time":3.387541293},
{"learn":[0.01217471113],"iteration":771,"passed_time":11.42186779,"remaining_time":3.373297742},
{"learn":[0.01215223704],"iteration":772,"passed_time":11.43519758,"remaining_time":3.358072251},
{"learn":[0.01213639643],"iteration":773,"passed_time":11.44836803,"remaining_time":3.342805136},
{"learn":[0.01210734858],"iteration":774,"passed_time":11.46659637,"remaining_time":3.329011849},
{"learn":[0.01207508331],"iteration":775,"passed_time":11.48162089,"remaining_time":3.31428232},
{"learn":[0.01204148107],"iteration":776,"passed_time":11.49850157,"remaining_time":3.30008475},
{"learn":[0.01202057835],"iteration":777,"passed_time":11.51442388,"remaining_time":3.285606815},
{"learn":[0.01199081513],"iteration":778,"passed_time":11.53260735,"remaining_time":3.271766654},
{"learn":[0.011961596],"iteration":779,"passed_time":11.54917894,"remaining_time":3.257460728},
{"learn":[0.01193958113],"iteration":780,"passed_time":11.56261952,"remaining_time":3.242271031},
{"learn":[0.01191148438],"iteration":781,"passed_time":11.58084086,"remaining_time":3.228418551},
{"learn":[0.01191145077],"iteration":782,"passed_time":11.58977547,"remaining_time":3.211981196},
{"learn":[0.01186685797],"iteration":783,"passed_time":11.60297375,"remaining_time":3.196737667},
{"learn":[0.01183185208],"iteration":784,"passed_time":11.61713045,"remaining_time":3.181761843},
{"learn":[0.01179733399],"iteration":785,"passed_time":11.63065269,"remaining_time":3.166615365},
{"learn":[0.01179732202],"iteration":786,"passed_time":11.63972822,"remaining_time":3.150269517},
{"learn":[0.01178506468],"iteration":787,"passed_time":11.65616486,"remaining_time":3.135922525},
{"learn":[0.01176300401],"iteration":788,"passed_time":11.67224625,"remaining_time":3.121475233},
{"learn":[0.01173295619],"iteration":789,"passed_time":11.68690407,"remaining_time":3.106645386},
{"learn":[0.01171336141],"iteration":790,"passed_time":11.70100943,"remaining_time":3.091670002},
{"learn":[0.01168033899],"iteration":791,"passed_time":11.71615367,"remaining_time":3.07696965},
{"learn":[0.01168031323],"iteration":792,"passed_time":11.72592081,"remaining_time":3.060864575},
{"learn":[0.01165791361],"iteration":793,"passed_time":11.74179091,"remaining_time":3.046358852},
{"learn":[0.01164149305],"iteration":794,"passed_time":11.75833618,"remaining_time":3.032023794},
{"learn":[0.01162459032],"iteration":795,"passed_time":11.77355724,"remaining_time":3.017343816},
{"learn":[0.01161924168],"iteration":796,"passed_time":11.78777411,"remaining_time":3.002406705},
{"learn":[0.01160341343],"iteration":797,"passed_time":11.80060636,"remaining_time":2.987120907},
{"learn":[0.01155980511],"iteration":798,"passed_time":11.81332323,"remaining_time":2.971812227},
{"learn":[0.01153714589],"iteration":799,"passed_time":11.82778501,"remaining_time":2.956946252},
{"learn":[0.0115219286],"iteration":800,"passed_time":11.84135429,"remaining_time":2.941859556},
{"learn":[0.01150481196],"iteration":801,"passed_time":11.8557579,"remaining_time":2.926982625},
{"learn":[0.01147658165],"iteration":802,"passed_time":11.87221917,"remaining_time":2.912611677},
{"learn":[0.01146990013],"iteration":803,"passed_time":11.88724836,"remaining_time":2.897886417},
{"learn":[0.01144071686],"iteration":804,"passed_time":11.90063115,"remaining_time":2.882761582},
{"learn":[0.0114254911],"iteration":805,"passed_time":11.9141566,"remaining_time":2.86767541},
{"learn":[0.01140922876],"iteration":806,"passed_time":11.92771234,"remaining_time":2.85260035},
{"learn":[0.01140894146],"iteration":807,"passed_time":11.93560117,"remaining_time":2.836182455},
{"learn":[0.01140507853],"iteration":808,"passed_time":11.95026453,"remaining_time":2.821385073},
{"learn":[0.01140504859],"iteration":809,"passed_time":11.95996429,"remaining_time":2.805423723},
{"learn":[0.01140142541],"iteration":810,"passed_time":11.97641802,"remaining_time":2.791051795},
{"learn":[0.0113796999],"iteration":811,"passed_time":11.99272974,"remaining_time":2.776641862},
{"learn":[0.0113709819],"iteration":812,"passed_time":12.00829197,"remaining_time":2.762054857},
{"learn":[0.0113603561],"iteration":813,"passed_time":12.02539869,"remaining_time":2.747818374},
{"learn":[0.01136033282],"iteration":814,"passed_time":12.03383764,"remaining_time":2.731607316},
{"learn":[0.01133439093],"iteration":815,"passed_time":12.0473013,"remaining_time":2.716548332},
{"learn":[0.01130961531],"iteration":816,"passed_time":12.05947438,"remaining_time":2.701204176},
{"learn":[0.01130959908],"iteration":817,"passed_time":12.06793887,"remaining_time":2.685042633},
{"learn":[0.01128388395],"iteration":818,"passed_time":12.08281427,"remaining_time":2.670316707},
{"learn":[0.0112495367],"iteration":819,"passed_time":12.09829325,"remaining_time":2.655722908},
{"learn":[0.01123209748],"iteration":820,"passed_time":12.11324582,"remaining_time":2.641012182},
{"learn":[0.01121046781],"iteration":821,"passed_time":12.12831234,"remaining_time":2.626325543},
{"learn":[0.01119176558],"iteration":822,"passed_time":12.14341378,"remaining_time":2.611645491},
{"learn":[0.01117560938],"iteration":823,"passed_time":12.16084,"remaining_time":2.597460971},
{"learn":[0.01115492083],"iteration":824,"passed_time":12.17509282,"remaining_time":2.582595447},
{"learn":[0.01112976586],"iteration":825,"passed_time":12.19156475,"remaining_time":2.568198871},
{"learn":[0.01112975212],"iteration":826,"passed_time":12.1996982,"remaining_time":2.552052949},
{"learn":[0.01111712444],"iteration":827,"passed_time":12.21547055,"remaining_time":2.537513207},
{"learn":[0.01110420839],"iteration":828,"passed_time":12.22930388,"remaining_time":2.522570522},
{"learn":[0.01108416088],"iteration":829,"passed_time":12.24668768,"remaining_time":2.508357717},
{"learn":[0.0110742775],"iteration":830,"passed_time":12.26284749,"remaining_time":2.493888358},
{"learn":[0.01106196893],"iteration":831,"passed_time":12.27632223,"remaining_time":2.478872758},
{"learn":[0.01105064135],"iteration":832,"passed_time":12.29178417,"remaining_time":2.464259251},
{"learn":[0.01102022743],"iteration":833,"passed_time":12.30481596,"remaining_time":2.449160011},
{"learn":[0.01100665003],"iteration":834,"passed_time":12.31902691,"remaining_time":2.43429873},
{"learn":[0.01100024714],"iteration":835,"passed_time":12.33431889,"remaining_time":2.419651074},
{"learn":[0.01098540854],"iteration":836,"passed_time":12.34747484,"remaining_time":2.404585901},
{"learn":[0.01095731587],"iteration":837,"passed_time":12.36064517,"remaining_time":2.389528064},
{"learn":[0.0109228309],"iteration":838,"passed_time":12.37923575,"remaining_time":2.375514847},
{"learn":[0.01092282525],"iteration":839,"passed_time":12.38792303,"remaining_time":2.359604387},
{"learn":[0.01092279847],"iteration":840,"passed_time":12.3979773,"remaining_time":2.343969548},
{"learn":[0.01090240993],"iteration":841,"passed_time":12.41453431,"remaining_time":2.329568196},
{"learn":[0.01088490337],"iteration":842,"passed_time":12.42833947,"remaining_time":2.314649225},
{"learn":[0.01087336501],"iteration":843,"passed_time":12.44516211,"remaining_time":2.300290627},
{"learn":[0.01085897594],"iteration":844,"passed_time":12.46051105,"remaining_time":2.285655873},
{"learn":[0.01085892592],"iteration":845,"passed_time":12.46839037,"remaining_time":2.269659713},
{"learn":[0.01082694719],"iteration":846,"passed_time":12.48441618,"remaining_time":2.25515428},
{"learn":[0.01082692012],"iteration":847,"passed_time":12.49298254,"remaining_time":2.239308191},
{"learn":[0.01082693236],"iteration":848,"passed_time":12.50138819,"remaining_time":2.223450668},
{"learn":[0.01082690504],"iteration":849,"passed_time":12.51072113,"remaining_time":2.207774317},
{"learn":[0.01080693944],"iteration":850,"passed_time":12.52478704,"remaining_time":2.192941561},
{"learn":[0.01080087766],"iteration":851,"passed_time":12.54072976,"remaining_time":2.178436626},
{"learn":[0.01077988147],"iteration":852,"passed_time":12.55252369,"remaining_time":2.163213343},
{"learn":[0.01075725433],"iteration":853,"passed_time":12.56746459,"remaining_time":2.1485361},
{"learn":[0.01073654757],"iteration":854,"passed_time":12.57912088,"remaining_time":2.133301202},
{"learn":[0.01072334934],"iteration":855,"passed_time":12.59418541,"remaining_time":2.118648013},
{"learn":[0.01070911822],"iteration":856,"passed_time":12.60684874,"remaining_time":2.103593197},
{"learn":[0.0106830646],"iteration":857,"passed_time":12.62132931,"remaining_time":2.088844711},
{"learn":[0.01066909081],"iteration":858,"passed_time":12.63482093,"remaining_time":2.073934518},
{"learn":[0.01065053001],"iteration":859,"passed_time":12.65004358,"remaining_time":2.05930942},
{"learn":[0.01062555736],"iteration":860,"passed_time":12.66456965,"remaining_time":2.044570477},
{"learn":[0.01061229782],"iteration":861,"passed_time":12.6812845,"remaining_time":2.030182437},
{"learn":[0.01060291988],"iteration":862,"passed_time":12.698597,"remaining_time":2.015883881},
{"learn":[0.0105781441],"iteration":863,"passed_time":12.71410969,"remaining_time":2.001295044},
{"learn":[0.01055076197],"iteration":864,"passed_time":12.72621074,"remaining_time":1.986171618},
{"learn":[0.01053317972],"iteration":865,"passed_time":12.74172047,"remaining_time":1.971582613},
{"learn":[0.01051377434],"iteration":866,"passed_time":12.75639462,"remaining_time":1.956863304},
{"learn":[0.01048337664],"iteration":867,"passed_time":12.77072748,"remaining_time":1.942092198},
{"learn":[0.01046424266],"iteration":868,"passed_time":12.78394585,"remaining_time":1.927154093},
{"learn":[0.01045078398],"iteration":869,"passed_time":12.79923888,"remaining_time":1.912529947},
{"learn":[0.0104376912],"iteration":870,"passed_time":12.81357491,"remaining_time":1.897762529},
{"learn":[0.01041568053],"iteration":871,"passed_time":12.82591174,"remaining_time":1.882702641},
{"learn":[0.01039205212],"iteration":872,"passed_time":12.83805429,"remaining_time":1.867620727},
{"learn":[0.01037994566],"iteration":873,"passed_time":12.85290077,"remaining_time":1.852935351},
{"learn":[0.01036984584],"iteration":874,"passed_time":12.86678293,"remaining_time":1.838111847},
{"learn":[0.01035270065],"iteration":875,"passed_time":12.8788691,"remaining_time":1.823036265},
{"learn":[0.01033152318],"iteration":876,"passed_time":12.89511082,"remaining_time":1.808550321},
{"learn":[0.01032299414],"iteration":877,"passed_time":12.90907773,"remaining_time":1.793744286},
{"learn":[0.01030158956],"iteration":878,"passed_time":12.92437492,"remaining_time":1.779123282},
{"learn":[0.01030155348],"iteration":879,"passed_time":12.93285511,"remaining_time":1.763571152},
{"learn":[0.01029616164],"iteration":880,"passed_time":12.95046858,"remaining_time":1.749268741},
{"learn":[0.01028959475],"iteration":881,"passed_time":12.9611998,"remaining_time":1.734038068},
{"learn":[0.01026695619],"iteration":882,"passed_time":12.97343543,"remaining_time":1.719016925},
{"learn":[0.01025917702],"iteration":883,"passed_time":12.98782266,"remaining_time":1.704284422},
{"learn":[0.01024479904],"iteration":884,"passed_time":13.00324064,"remaining_time":1.689686637},
{"learn":[0.01022238308],"iteration":885,"passed_time":13.01609152,"remaining_time":1.674756696},
{"learn":[0.01020486377],"iteration":886,"passed_time":13.02956747,"remaining_time":1.659911076},
{"learn":[0.01018242911],"iteration":887,"passed_time":13.04350129,"remaining_time":1.645126289},
{"learn":[0.01017453926],"iteration":888,"passed_time":13.05733816,"remaining_time":1.630331311},
{"learn":[0.01015373635],"iteration":889,"passed_time":13.07068299,"remaining_time":1.615477673},
{"learn":[0.01012491176],"iteration":890,"passed_time":13.08417811,"remaining_time":1.600645806},
{"learn":[0.01011645971],"iteration":891,"passed_time":13.09971042,"remaining_time":1.586063593},
{"learn":[0.01010311681],"iteration":892,"passed_time":13.11208563,"remaining_time":1.571100966},
{"learn":[0.01007266401],"iteration":893,"passed_time":13.1239238,"remaining_time":1.556080451},
{"learn":[0.01004994496],"iteration":894,"passed_time":13.14104214,"remaining_time":1.541686509},
{"learn":[0.01002918268],"iteration":895,"passed_time":13.1555243,"remaining_time":1.526980499},
{"learn":[0.01000457466],"iteration":896,"passed_time":13.17006887,"remaining_time":1.512282155},
{"learn":[0.009989074475],"iteration":897,"passed_time":13.18502606,"remaining_time":1.497631022},
{"learn":[0.00996946455],"iteration":898,"passed_time":13.19946638,"remaining_time":1.48292114},
{"learn":[0.009946968876],"iteration":899,"passed_time":13.21239075,"remaining_time":1.468043417},
{"learn":[0.009933729053],"iteration":900,"passed_time":13.22463784,"remaining_time":1.453095612},
{"learn":[0.009919187106],"iteration":901,"passed_time":13.2402294,"remaining_time":1.438517163},
{"learn":[0.009891031473],"iteration":902,"passed_time":13.25358823,"remaining_time":1.423696631},
{"learn":[0.009862110467],"iteration":903,"passed_time":13.26804272,"remaining_time":1.408995687},
{"learn":[0.009839711783],"iteration":904,"passed_time":13.28298607,"remaining_time":1.394346605},
{"learn":[0.009820638624],"iteration":905,"passed_time":13.29792489,"remaining_time":1.379696402},
{"learn":[0.009807776533],"iteration":906,"passed_time":13.31336783,"remaining_time":1.365097253},
{"learn":[0.009791781914],"iteration":907,"passed_time":13.32701478,"remaining_time":1.350314273},
{"learn":[0.009768401214],"iteration":908,"passed_time":13.3432793,"remaining_time":1.335795837},
{"learn":[0.009753419146],"iteration":909,"passed_time":13.35962594,"remaining_time":1.321281686},
{"learn":[0.009725161441],"iteration":910,"passed_time":13.3737483,"remaining_time":1.306546212},
{"learn":[0.009725163008],"iteration":911,"passed_time":13.38173096,"remaining_time":1.291219654},
{"learn":[0.00971366932],"iteration":912,"passed_time":13.39661015,"remaining_time":1.276566356},
{"learn":[0.00969589471],"iteration":913,"passed_time":13.41079843,"remaining_time":1.261847555},
{"learn":[0.009676788374],"iteration":914,"passed_time":13.42409576,"remaining_time":1.247047147},
{"learn":[0.009676691213],"iteration":915,"passed_time":13.43242516,"remaining_time":1.231794447},
{"learn":[0.009662282041],"iteration":916,"passed_time":13.4488153,"remaining_time":1.217286445},
{"learn":[0.009649120028],"iteration":917,"passed_time":13.46331196,"remaining_time":1.202605208},
{"learn":[0.009621022956],"iteration":918,"passed_time":13.47770107,"remaining_time":1.187914893},
{"learn":[0.009621000546],"iteration":919,"passed_time":13.48631293,"remaining_time":1.172722863},
{"learn":[0.009620982706],"iteration":920,"passed_time":13.49502529,"remaining_time":1.157553744},
{"learn":[0.009600463949],"iteration":921,"passed_time":13.50782145,"remaining_time":1.142744114},
{"learn":[0.009587048359],"iteration":922,"passed_time":13.52281623,"remaining_time":1.128122264},
{"learn":[0.009563547887],"iteration":923,"passed_time":13.53615343,"remaining_time":1.113363269},
{"learn":[0.009551070213],"iteration":924,"passed_time":13.54863806,"remaining_time":1.098538221},
{"learn":[0.00952874441],"iteration":925,"passed_time":13.56185772,"remaining_time":1.083776967},
{"learn":[0.009500680865],"iteration":926,"passed_time":13.57708578,"remaining_time":1.069177198},
{"learn":[0.009478946285],"iteration":927,"passed_time":13.59216389,"remaining_time":1.05456444},
{"learn":[0.009448375212],"iteration":928,"passed_time":13.60559872,"remaining_time":1.039825091},
{"learn":[0.009428303825],"iteration":929,"passed_time":13.619391,"remaining_time":1.025115452},
{"learn":[0.009408049569],"iteration":930,"passed_time":13.6341692,"remaining_time":1.010480853},
{"learn":[0.009381253762],"iteration":931,"passed_time":13.64716465,"remaining_time":0.9957158759},
{"learn":[0.009363843004],"iteration":932,"passed_time":13.66243563,"remaining_time":0.9811181001},
{"learn":[0.009347529019],"iteration":933,"passed_time":13.67761099,"remaining_time":0.9665121257},
{"learn":[0.009331830359],"iteration":934,"passed_time":13.68903379,"remaining_time":0.9516440602},
{"learn":[0.009309132828],"iteration":935,"passed_time":13.70423231,"remaining_time":0.9370415257},
{"learn":[0.009296343314],"iteration":936,"passed_time":13.71703894,"remaining_time":0.9222768976},
{"learn":[0.009276068653],"iteration":937,"passed_time":13.73077401,"remaining_time":0.9075778132},
{"learn":[0.009276035311],"iteration":938,"passed_time":13.73908716,"remaining_time":0.8925285592},
{"learn":[0.009265230488],"iteration":939,"passed_time":13.75313186,"remaining_time":0.8778594806},
{"learn":[0.009239651648],"iteration":940,"passed_time":13.76943234,"remaining_time":0.8633331647},
{"learn":[0.009222471898],"iteration":941,"passed_time":13.78276046,"remaining_time":0.8486200706},
{"learn":[0.009207061636],"iteration":942,"passed_time":13.79584,"remaining_time":0.8338948884},
{"learn":[0.00919272114],"iteration":943,"passed_time":13.81019494,"remaining_time":0.8192488525},
{"learn":[0.009182258865],"iteration":944,"passed_time":13.82285465,"remaining_time":0.8045047679},
{"learn":[0.009166524137],"iteration":945,"passed_time":13.83744784,"remaining_time":0.7898754583},
{"learn":[0.00914777936],"iteration":946,"passed_time":13.85031955,"remaining_time":0.7751498798},
{"learn":[0.009147772542],"iteration":947,"passed_time":13.85821571,"remaining_time":0.7601552919},
{"learn":[0.009133578824],"iteration":948,"passed_time":13.87350665,"remaining_time":0.7455730652},
{"learn":[0.00911858546],"iteration":949,"passed_time":13.88867829,"remaining_time":0.7309830681},
{"learn":[0.00910462814],"iteration":950,"passed_time":13.90198,"remaining_time":0.7162954994},
{"learn":[0.009091792425],"iteration":951,"passed_time":13.91749223,"remaining_time":0.7017222972},
{"learn":[0.009071458072],"iteration":952,"passed_time":13.93148301,"remaining_time":0.6870720897},
{"learn":[0.009058081261],"iteration":953,"passed_time":13.94545179,"remaining_time":0.6724222038},
{"learn":[0.009047174035],"iteration":954,"passed_time":13.95930803,"remaining_time":0.6577684413},
{"learn":[0.009027202915],"iteration":955,"passed_time":13.97471922,"remaining_time":0.643187914},
{"learn":[0.009016060005],"iteration":956,"passed_time":13.99031233,"remaining_time":0.6286138245},
{"learn":[0.008997131994],"iteration":957,"passed_time":14.00584268,"remaining_time":0.6140348566},
{"learn":[0.008984568718],"iteration":958,"passed_time":14.02243199,"remaining_time":0.5994991778},
{"learn":[0.008984518714],"iteration":959,"passed_time":14.03092831,"remaining_time":0.5846220128},
{"learn":[0.008966395836],"iteration":960,"passed_time":14.04519892,"remaining_time":0.569992464},
{"learn":[0.00895049988],"iteration":961,"passed_time":14.06010965,"remaining_time":0.5553889468},
{"learn":[0.008934219229],"iteration":962,"passed_time":14.07867841,"remaining_time":0.5409253385},
{"learn":[0.008918741295],"iteration":963,"passed_time":14.09813828,"remaining_time":0.5264864916},
{"learn":[0.00889963907],"iteration":964,"passed_time":14.11278347,"remaining_time":0.5118626129},
{"learn":[0.008878899859],"iteration":965,"passed_time":14.12602626,"remaining_time":0.49718933},
{"learn":[0.00886395705],"iteration":966,"passed_time":14.14287889,"remaining_time":0.482642196},
{"learn":[0.008845433319],"iteration":967,"passed_time":14.15539806,"remaining_time":0.4679470434},
{"learn":[0.008831061741],"iteration":968,"passed_time":14.17046446,"remaining_time":0.4533378723},
{"learn":[0.00880887042],"iteration":969,"passed_time":14.18888226,"remaining_time":0.43883141},
{"learn":[0.008792489479],"iteration":970,"passed_time":14.2014578,"remaining_time":0.4241424059},
{"learn":[0.00877743823],"iteration":971,"passed_time":14.21578487,"remaining_time":0.4095082061},
{"learn":[0.008758476981],"iteration":972,"passed_time":14.23011861,"remaining_time":0.3948748226},
{"learn":[0.008746201084],"iteration":973,"passed_time":14.24362572,"remaining_time":0.3802199885},
{"learn":[0.008733930305],"iteration":974,"passed_time":14.26004795,"remaining_time":0.3656422551},
{"learn":[0.008718070206],"iteration":975,"passed_time":14.2766298,"remaining_time":0.3510646671},
{"learn":[0.008711179208],"iteration":976,"passed_time":14.28760881,"remaining_time":0.3363510773},
{"learn":[0.008705039402],"iteration":977,"passed_time":14.2990004,"remaining_time":0.3216544057},
{"learn":[0.008683746249],"iteration":978,"passed_time":14.3132853,"remaining_time":0.3070265489},
{"learn":[0.008670093824],"iteration":979,"passed_time":14.32523793,"remaining_time":0.2923517945},
{"learn":[0.00866982244],"iteration":980,"passed_time":14.33352883,"remaining_time":0.2776116696},
{"learn":[0.008669781808],"iteration":981,"passed_time":14.34312602,"remaining_time":0.2629086236},
{"learn":[0.008649085454],"iteration":982,"passed_time":14.35727634,"remaining_time":0.2482947079},
{"learn":[0.008631888745],"iteration":983,"passed_time":14.37041609,"remaining_time":0.2336653023},
{"learn":[0.008631870421],"iteration":984,"passed_time":14.37848508,"remaining_time":0.2189617017},
{"learn":[0.008622740137],"iteration":985,"passed_time":14.39662991,"remaining_time":0.2044146235},
{"learn":[0.008610553152],"iteration":986,"passed_time":14.40859988,"remaining_time":0.1897789244},
{"learn":[0.00861053722],"iteration":987,"passed_time":14.4166542,"remaining_time":0.1751010631},
{"learn":[0.008594064811],"iteration":988,"passed_time":14.42980361,"remaining_time":0.1604932656},
{"learn":[0.008582144699],"iteration":989,"passed_time":14.44622663,"remaining_time":0.1459214811},
{"learn":[0.008560161031],"iteration":990,"passed_time":14.46048282,"remaining_time":0.1313262819},
{"learn":[0.008543268891],"iteration":991,"passed_time":14.47264095,"remaining_time":0.1167148464},
{"learn":[0.00852927649],"iteration":992,"passed_time":14.4857362,"remaining_time":0.1021149581},
{"learn":[0.008529276701],"iteration":993,"passed_time":14.49622817,"remaining_time":0.08750238331},
{"learn":[0.008515538959],"iteration":994,"passed_time":14.50962783,"remaining_time":0.07291270266},
{"learn":[0.008502169652],"iteration":995,"passed_time":14.52247383,"remaining_time":0.05832318806},
{"learn":[0.008483996238],"iteration":996,"passed_time":14.5347955,"remaining_time":0.04373559327},
{"learn":[0.008483995532],"iteration":997,"passed_time":14.54169507,"remaining_time":0.0291416735},
{"learn":[0.00847234],"iteration":998,"passed_time":14.55876267,"remaining_time":0.01457333601},
{"learn":[0.008452349834],"iteration":999,"passed_time":14.57082763,"remaining_time":0}
]}